Workbook

Sheet January
A1: Product Name | B1: Product Type | C1: Opening Stocks | D1: Purchases | E1: Closing Stock | F1: Units Sold | G1: Purchase Price | H1: Selling Price | I1: Total Revenue | J1: Total Cost | K1: Profit
A2: Classmate Pulse 6 subject spiral Notebook (300 pages) (240mm X 180mm) | B2: Spiral Notebook | C2: 42 | D2: 22 | E2: =(D2+C2) -F2 -> 46 | F2: 18 | G2: 90 | H2: 120 | I2: =F2*H2 -> 2160 | J2: =F2*G2 -> 1620 | K2: =I2-J2 -> 540
A3: Classmate Pulse 6 subject spiral Notebook (300 pages) (267mm X 203mm) | B3: Spiral Notebook | C3: 39 | D3: 17 | E3: =(D3+C3) -F3 -> 42 | F3: 14 | G3: 135 | H3: 160 | I3: =F3*H3 -> 2240 | J3: =F3*G3 -> 1890 | K3: =I3-J3 -> 350
A4: Classmate Pulse 6 subject spiral Notebook (300 pages) (297mm X 210mm) | B4: Spiral Notebook | C4: 52 | D4: 15 | E4: =(D4+C4) -F4 -> 51 | F4: 16 | G4: 165 | H4: 185 | I4: =F4*H4 -> 2960 | J4: =F4*G4 -> 2640 | K4: =I4-J4 -> 320
A5: Classmate Notebook Singleline Ruled (120 pages) (240mm X 180mm) | B5: Ruled Notebook | C5: 34 | D5: 20 | E5: =(D5+C5) -F5 -> 39 | F5: 15 | G5: 25 | H5: 35 | I5: =F5*H5 -> 525 | J5: =F5*G5 -> 375 | K5: =I5-J5 -> 150
A6: Classmate Notebook Singleline Ruled (172 pages) (272mm X 167mm) | B6: Ruled Notebook | C6: 38 | D6: 23 | E6: =(D6+C6) -F6 -> 42 | F6: 19 | G6: 30 | H6: 55 | I6: =F6*H6 -> 1045 | J6: =F6*G6 -> 570 | K6: =I6-J6 -> 475
A7: Navneet Notebook (92 pages) (180mm X 240mm) | B7: Ruled Notebook | C7: 29 | D7: 15 | E7: =(D7+C7) -F7 -> 32 | F7: 12 | G7: 18 | H7: 30 | I7: =F7*H7 -> 360 | J7: =F7*G7 -> 216 | K7: =I7-J7 -> 144
A8: Navneet Notebook (172 pages) (210mm X 297mm) | B8: Ruled Notebook | C8: 45 | D8: 18 | E8: =(D8+C8) -F8 -> 46 | F8: 17 | G8: 50 | H8: 65 | I8: =F8*H8 -> 1105 | J8: =F8*G8 -> 850 | K8: =I8-J8 -> 255
A9: Classmate Notebook Unruled (168 pages) (240mm X 180mm) | B9: Unruled Notebook | C9: 33 | D9: 16 | E9: =(D9+C9) -F9 -> 36 | F9: 13 | G9: 35 | H9: 50 | I9: =F9*H9 -> 650 | J9: =F9*G9 -> 455 | K9: =I9-J9 -> 195
A10: Yuva Notebook Unruled (180 pages) (240mm X 180mm) | B10: Unruled Notebook | C10: 31 | D10: 10 | E10: =(D10+C10) -F10 -> 28 | F10: 13 | G10: 22 | H10: 40 | I10: =F10*H10 -> 520 | J10: =F10*G10 -> 286 | K10: =I10-J10 -> 234
A11: Classmate LongBook (384 pages) (297mm X 210mm) | B11: Register | C11: 22 | D11: 10 | E11: =(D11+C11) -F11 -> 22 | F11: 10 | G11: 190 | H11: 220 | I11: =F11*H11 -> 2200 | J11: =F11*G11 -> 1900 | K11: =I11-J11 -> 300
A12: Classmate LongBook (140 pages) (297mm X 210mm) | B12: Register | C12: 27 | D12: 12 | E12: =(D12+C12) -F12 -> 27 | F12: 12 | G12: 65 | H12: 85 | I12: =F12*H12 -> 1020 | J12: =F12*G12 -> 780 | K12: =I12-J12 -> 240
A13: Navneet LongBook (76 pages) (297mm X 210mm) | B13: Register | C13: 19 | D13: 10 | E13: =(D13+C13) -F13 -> 20 | F13: 9 | G13: 30 | H13: 42 | I13: =F13*H13 -> 378 | J13: =F13*G13 -> 270 | K13: =I13-J13 -> 108
... A65: Edet A4 White Sheets (150 gsm) | B65: A4 Sheets | C65: 41 | D65: 24 | E65: =(D65+C65) -F65 -> 45 | F65: 20 | G65: 2 | H65: 5 | I65: =F65*H65 -> 100 | J65: =F65*G65 -> 40 | K65: =I65-J65 -> 60
H66: TOTAL

Sheet February
A1: Product Name | B1: Product Type | C1: Opening Stocks | D1: Purchases | E1: Closing Stock | F1: Units Sold | G1: Purchase Price | H1: Selling Price | I1: Total Revenue | J1: Total Cost | K1: Profit
A2: Classmate Pulse 6 subject spiral Notebook (300 pages) (240mm X 180mm) | B2: Spiral Notebook | C2: 44 | D2: 13 | E2: =C2+D2-F2 -> 45 | F2: 12 | G2: 90 | H2: 120 | I2: =F2*H2 -> 1440 | J2: =F2*G2 -> 1080 | K2: =I2-J2 -> 360
A3: Classmate Pulse 6 subject spiral Notebook (300 pages) (267mm X 203mm) | B3: Spiral Notebook | C3: 40 | D3: 9 | E3: =C3+D3-F3 -> 40 | F3: 9 | G3: 135 | H3: 160 | I3: =F3*H3 -> 1440 | J3: =F3*G3 -> 1215 | K3: =I3-J3 -> 225
A4: Classmate Pulse 6 subject spiral Notebook (300 pages) (297mm X 210mm) | B4: Spiral Notebook | C4: 51 | D4: 12 | E4: =C4+D4-F4 -> 53 | F4: 10 | G4: 165 | H4: 185 | I4: =F4*H4 -> 1850 | J4: =F4*G4 -> 1650 | K4: =I4-J4 -> 200
A5: Classmate Notebook Singleline Ruled (120 pages) (240mm X 180mm) | B5: Ruled Notebook | C5: 39 | D5: 10 | E5: =C5+D5-F5 -> 37 | F5: 12 | G5: 25 | H5: 35 | I5: =F5*H5 -> 420 | J5: =F5*G5 -> 300 | K5: =I5-J5 -> 120
A6: Classmate Notebook Singleline Ruled (172 pages) (272mm X 167mm) | B6: Ruled Notebook | C6: 44 | D6: 15 | E6: =C6+D6-F6 -> 46 | F6: 13 | G6: 30 | H6: 55 | I6: =F6*H6 -> 715 | J6: =F6*G6 -> 390 | K6: =I6-J6 -> 325
A7: Navneet Notebook (92 pages) (180mm X 240mm) | B7: Ruled Notebook | C7: 32 | D7: 18 | E7: =C7+D7-F7 -> 41 | F7: 9 | G7: 18 | H7: 30 | I7: =F7*H7 -> 270 | J7: =F7*G7 -> 162 | K7: =I7-J7 -> 108
A8: Navneet Notebook (172 pages) (210mm X 297mm) | B8: Ruled Notebook | C8: 48 | D8: 16 | E8: =C8+D8-F8 -> 51 | F8: 13 | G8: 50 | H8: 65 | I8: =F8*H8 -> 845 | J8: =F8*G8 -> 650 | K8: =I8-J8 -> 195
A9: Classmate Notebook Unruled (168 pages) (240mm X 180mm) | B9: Unruled Notebook | C9: 35 | D9: 11 | E9: =C9+D9-F9 -> 39 | F9: 7 | G9: 35 | H9: 50 | I9: =F9*H9 -> 350 | J9: =F9*G9 -> 245 | K9: =I9-J9 -> 105
A10: Yuva Notebook Unruled (180 pages) (240mm X 180mm) | B10: Unruled Notebook | C10: 28 | D10: 10 | E10: =C10+D10-F10 -> 32 | F10: 6 | G10: 22 | H10: 40 | I10: =F10*H10 -> 240 | J10: =F10*G10 -> 132 | K10: =I10-J10 -> 108
A11: Classmate LongBook (384 pages) (297mm X 210mm) | B11: Register | C11: 22 | D11: 20 | E11: =C11+D11-F11 -> 32 | F11: 10 | G11: 190 | H11: 220 | I11: =F11*H11 -> 2200 | J11: =F11*G11 -> 1900 | K11: =I11-J11 -> 300
A12: Classmate LongBook (140 pages) (297mm X 210mm) | B12: Register | C12: 30 | D12: 23 | E12: =C12+D12-F12 -> 45 | F12: 8 | G12: 65 | H12: 85 | I12: =F12*H12 -> 680 | J12: =F12*G12 -> 520 | K12: =I12-J12 -> 160
A13: Navneet LongBook (76 pages) (297mm X 210mm) | B13: Register | C13: 20 | D13: 17 | E13: =C13+D13-F13 -> 32 | F13: 5 | G13: 30 | H13: 42 | I13: =F13*H13 -> 210 | J13: =F13*G13 -> 150 | K13: =I13-J13 -> 60
... A65: Edet A4 White Sheets (150 gsm) | B65: A4 Sheets | C65: 46 | D65: 24 | E65: =C65+D65-F65 -> 55 | F65: 15 | G65: 2 | H65: 5 | I65: =F65*H65 -> 75 | J65: =F65*G65 -> 30 | K65: =I65-J65 -> 45

Sheet March
A1: Product Name | B1: Product Type | C1: Opening Stocks | D1: Purchases | E1: Closing Stock | F1: Units Sold | G1: Purchase Price | H1: Selling Price | I1: Total Revenue | J1: Total Cost | K1: Profit
A2: Classmate Pulse 6 subject spiral Notebook (300 pages) (240mm X 180mm) | B2: Spiral Notebook | C2: 47 | D2: 23 | E2: =C2+D2-F2 -> 47 | F2: 23 | G2: 90 | H2: 120 | I2: =F2*H2 -> 2760 | J2: =F2*G2 -> 2070 | K2: =I2-J2 -> 690
A3: Classmate Pulse 6 subject spiral Notebook (300 pages) (267mm X 203mm) | B3: Spiral Notebook | C3: 41 | D3: 20 | E3: =C3+D3-F3 -> 43 | F3: 18 | G3: 135 | H3: 160 | I3: =F3*H3 -> 2880 | J3: =F3*G3 -> 2430 | K3: =I3-J3 -> 450
A4: Classmate Pulse 6 subject spiral Notebook (300 pages) (297mm X 210mm) | B4: Spiral Notebook | C4: 51 | D4: 22 | E4: =C4+D4-F4 -> 56 | F4: 17 | G4: 165 | H4: 185 | I4: =F4*H4 -> 3145 | J4: =F4*G4 -> 2805 | K4: =I4-J4 -> 340
A5: Classmate Notebook Singleline Ruled (120 pages) (240mm X 180mm) | B5: Ruled Notebook | C5: 37 | D5: 24 | E5: =C5+D5-F5 -> 43 | F5: 18 | G5: 25 | H5: 35 | I5: =F5*H5 -> 630 | J5: =F5*G5 -> 450 | K5: =I5-J5 -> 180
A6: Classmate Notebook Singleline Ruled (172 pages) (272mm X 167mm) | B6: Ruled Notebook | C6: 46 | D6: 28 | E6: =C6+D6-F6 -> 50 | F6: 24 | G6: 30 | H6: 55 | I6: =F6*H6 -> 1320 | J6: =F6*G6 -> 720 | K6: =I6-J6 -> 600
A7: Navneet Notebook (92 pages) (180mm X 240mm) | B7: Ruled Notebook | C7: 38 | D7: 25 | E7: =C7+D7-F7 -> 41 | F7: 22 | G7: 18 | H7: 30 | I7: =F7*H7 -> 660 | J7: =F7*G7 -> 396 | K7: =I7-J7 -> 264
A8: Navneet Notebook (172 pages) (210mm X 297mm) | B8: Ruled Notebook | C8: 50 | D8: 25 | E8: =C8+D8-F8 -> 61 | F8: 14 | G8: 50 | H8: 65 | I8: =F8*H8 -> 910 | J8: =F8*G8 -> 700 | K8: =I8-J8 -> 210
A9: Classmate Notebook Unruled (168 pages) (240mm X 180mm) | B9: Unruled Notebook | C9: 38 | D9: 12 | E9: =C9+D9-F9 -> 38 | F9: 12 | G9: 35 | H9: 50 | I9: =F9*H9 -> 600 | J9: =F9*G9 -> 420 | K9: =I9-J9 -> 180
A10: Yuva Notebook Unruled (180 pages) (240mm X 180mm) | B10: Unruled Notebook | C10: 32 | D10: 14 | E10: =C10+D10-F10 -> 35 | F10: 11 | G10: 22 | H10: 40 | I10: =F10*H10 -> 440 | J10: =F10*G10 -> 242 | K10: =I10-J10 -> 198
A11: Classmate LongBook (384 pages) (297mm X 210mm) | B11: Register | C11: 32 | D11: 18 | E11: =C11+D11-F11 -> 36 | F11: 14 | G11: 190 | H11: 220 | I11: =F11*H11 -> 3080 | J11: =F11*G11 -> 2660 | K11: =I11-J11 -> 420
A12: Classmate LongBook (140 pages) (297mm X 210mm) | B12: Register | C12: 42 | D12: 26 | E12: =C12+D12-F12 -> 53 | F12: 15 | G12: 65 | H12: 85 | I12: =F12*H12 -> 1275 | J12: =F12*G12 -> 975 | K12: =I12-J12 -> 300
A13: Navneet LongBook (76 pages) (297mm X 210mm) | B13: Register | C13: 35 | D13: 23 | E13: =C13+D13-F13 -> 41 | F13: 17 | G13: 30 | H13: 42 | I13: =F13*H13 -> 714 | J13: =F13*G13 -> 510 | K13: =I13-J13 -> 204
... A65: Edet A4 White Sheets (150 gsm) | B65: A4 Sheets | C65: 56 | D65: 18 | E65: =C65+D65-F65 -> 56 | F65: 18 | G65: 2 | H65: 5 | I65: =F65*H65 -> 90 | J65: =F65*G65 -> 36 | K65: =I65-J65 -> 54

Sheet April
A1: Product Name | B1: Product Type | C1: Opening Stocks | D1: Purchases | E1: Closing Stock | F1: Units Sold | G1: Purchase Price | H1: Selling Price | I1: Total Revenue | J1: Total Cost | K1: Profit
A2: Classmate Pulse 6 subject spiral Notebook (300 pages) (240mm X 180mm) | B2: Spiral Notebook | C2: 49 | D2: 52 | E2: =C2+D2-F2 -> 52 | F2: 49 | G2: 90 | H2: 120 | I2: =F2*H2 -> 5880 | J2: =F2*G2 -> 4410 | K2: =I2-J2 -> 1470
A3: Classmate Pulse 6 subject spiral Notebook (300 pages) (267mm X 203mm) | B3: Spiral Notebook | C3: 43 | D3: 48 | E3: =C3+D3-F3 -> 46 | F3: 45 | G3: 135 | H3: 160 | I3: =F3*H3 -> 7200 | J3: =F3*G3 -> 6075 | K3: =I3-J3 -> 1125
A4: Classmate Pulse 6 subject spiral Notebook (300 pages) (297mm X 210mm) | B4: Spiral Notebook | C4: 54 | D4: 40 | E4: =C4+D4-F4 -> 57 | F4: 37 | G4: 165 | H4: 185 | I4: =F4*H4 -> 6845 | J4: =F4*G4 -> 6105 | K4: =I4-J4 -> 740
A5: Classmate Notebook Singleline Ruled (120 pages) (240mm X 180mm) | B5: Ruled Notebook | C5: 39 | D5: 43 | E5: =C5+D5-F5 -> 41 | F5: 41 | G5: 25 | H5: 35 | I5: =F5*H5 -> 1435 | J5: =F5*G5 -> 1025 | K5: =I5-J5 -> 410
A6: Classmate Notebook Singleline Ruled (172 pages) (272mm X 167mm) | B6: Ruled Notebook | C6: 52 | D6: 38 | E6: =C6+D6-F6 -> 43 | F6: 47 | G6: 30 | H6: 55 | I6: =F6*H6 -> 2585 | J6: =F6*G6 -> 1410 | K6: =I6-J6 -> 1175
A7: Navneet Notebook (92 pages) (180mm X 240mm) | B7: Ruled Notebook | C7: 41 | D7: 51 | E7: =C7+D7-F7 -> 44 | F7: 48 | G7: 18 | H7: 30 | I7: =F7*H7 -> 1440 | J7: =F7*G7 -> 864 | K7: =I7-J7 -> 576
A8: Navneet Notebook (172 pages) (210mm X 297mm) | B8: Ruled Notebook | C8: 61 | D8: 60 | E8: =C8+D8-F8 -> 68 | F8: 53 | G8: 50 | H8: 65 | I8: =F8*H8 -> 3445 | J8: =F8*G8 -> 2650 | K8: =I8-J8 -> 795
A9: Classmate Notebook Unruled (168 pages) (240mm X 180mm) | B9: Unruled Notebook | C9: 41 | D9: 28 | E9: =C9+D9-F9 -> 38 | F9: 31 | G9: 35 | H9: 50 | I9: =F9*H9 -> 1550 | J9: =F9*G9 -> 1085 | K9: =I9-J9 -> 465
A10: Yuva Notebook Unruled (180 pages) (240mm X 180mm) | B10: Unruled Notebook | C10: 36 | D10: 43 | E10: =C10+D10-F10 -> 45 | F10: 34 | G10: 22 | H10: 40 | I10: =F10*H10 -> 1360 | J10: =F10*G10 -> 748 | K10: =I10-J10 -> 612
A11: Classmate LongBook (384 pages) (297mm X 210mm) | B11: Register | C11: 38 | D11: 36 | E11: =C11+D11-F11 -> 43 | F11: 31 | G11: 190 | H11: 220 | I11: =F11*H11 -> 6820 | J11: =F11*G11 -> 5890 | K11: =I11-J11 -> 930
A12: Classmate LongBook (140 pages) (297mm X 210mm) | B12: Register | C12: 52 | D12: 27 | E12: =C12+D12-F12 -> 50 | F12: 29 | G12: 65 | H12: 85 | I12: =F12*H12 -> 2465 | J12: =F12*G12 -> 1885 | K12: =I12-J12 -> 580
A13: Navneet LongBook (76 pages) (297mm X 210mm) | B13: Register | C13: 43 | D13: 50 | E13: =C13+D13-F13 -> 50 | F13: 43 | G13: 30 | H13: 42 | I13: =F13*H13 -> 1806 | J13: =F13*G13 -> 1290 | K13: =I13-J13 -> 516
... A65: Edet A4 White Sheets (150 gsm) | B65: A4 Sheets | C65: 58 | D65: 35 | E65: =C65+D65-F65 -> 67 | F65: 26 | G65: 2 | H65: 5 | I65: =F65*H65 -> 130 | J65: =F65*G65 -> 52 | K65: =I65-J65 -> 78

Sheet May
A1: Product Name | B1: Product Type | C1: Opening Stocks | D1: Purchases | E1: Closing Stock | F1: Units Sold | G1: Purchase Price | H1: Selling Price | I1: Total Revenue | J1: Total Cost | K1: Profit
A2: Classmate Pulse 6 subject spiral Notebook (300 pages) (240mm X 180mm) | B2: Spiral Notebook | C2: 50 | D2: 42 | E2: =C2+D2-F2 -> 65 | F2: 27 | G2: 90 | H2: 120 | I2: =F2*H2 -> 3240 | J2: =F2*G2 -> 2430 | K2: =I2-J2 -> 810
A3: Classmate Pulse 6 subject spiral Notebook (300 pages) (267mm X 203mm) | B3: Spiral Notebook | C3: 48 | D3: 28 | E3: =C3+D3-F3 -> 54 | F3: 22 | G3: 135 | H3: 160 | I3: =F3*H3 -> 3520 | J3: =F3*G3 -> 2970 | K3: =I3-J3 -> 550
A4: Classmate Pulse 6 subject spiral Notebook (300 pages) (297mm X 210mm) | B4: Spiral Notebook | C4: 57 | D4: 43 | E4: =C4+D4-F4 -> 77 | F4: 23 | G4: 165 | H4: 185 | I4: =F4*H4 -> 4255 | J4: =F4*G4 -> 3795 | K4: =I4-J4 -> 460
A5: Classmate Notebook Singleline Ruled (120 pages) (240mm X 180mm) | B5: Ruled Notebook | C5: 38 | D5: 27 | E5: =C5+D5-F5 -> 44 | F5: 21 | G5: 25 | H5: 35 | I5: =F5*H5 -> 735 | J5: =F5*G5 -> 525 | K5: =I5-J5 -> 210
A6: Classmate Notebook Singleline Ruled (172 pages) (272mm X 167mm) | B6: Ruled Notebook | C6: 45 | D6: 38 | E6: =C6+D6-F6 -> 58 | F6: 25 | G6: 30 | H6: 55 | I6: =F6*H6 -> 1375 | J6: =F6*G6 -> 750 | K6: =I6-J6 -> 625
A7: Navneet Notebook (92 pages) (180mm X 240mm) | B7: Ruled Notebook | C7: 43 | D7: 40 | E7: =C7+D7-F7 -> 56 | F7: 27 | G7: 18 | H7: 30 | I7: =F7*H7 -> 810 | J7: =F7*G7 -> 486 | K7: =I7-J7 -> 324
A8: Navneet Notebook (172 pages) (210mm X 297mm) | B8: Ruled Notebook | C8: 68 | D8: 44 | E8: =C8+D8-F8 -> 88 | F8: 24 | G8: 50 | H8: 65 | I8: =F8*H8 -> 1560 | J8: =F8*G8 -> 1200 | K8: =I8-J8 -> 360
A9: Classmate Notebook Unruled (168 pages) (240mm X 180mm) | B9: Unruled Notebook | C9: 40 | D9: 32 | E9: =C9+D9-F9 -> 53 | F9: 19 | G9: 35 | H9: 50 | I9: =F9*H9 -> 950 | J9: =F9*G9 -> 665 | K9: =I9-J9 -> 285
A10: Yuva Notebook Unruled (180 pages) (240mm X 180mm) | B10: Unruled Notebook | C10: 42 | D10: 33 | E10: =C10+D10-F10 -> 58 | F10: 17 | G10: 22 | H10: 40 | I10: =F10*H10 -> 680 | J10: =F10*G10 -> 374 | K10: =I10-J10 -> 306
A11: Classmate LongBook (384 pages) (297mm X 210mm) | B11: Register | C11: 42 | D11: 21 | E11: =C11+D11-F11 -> 49 | F11: 14 | G11: 190 | H11: 220 | I11: =F11*H11 -> 3080 | J11: =F11*G11 -> 2660 | K11: =I11-J11 -> 420
A12: Classmate LongBook (140 pages) (297mm X 210mm) | B12: Register | C12: 53 | D12: 34 | E12: =C12+D12-F12 -> 64 | F12: 23 | G12: 65 | H12: 85 | I12: =F12*H12 -> 1955 | J12: =F12*G12 -> 1495 | K12: =I12-J12 -> 460
A13: Navneet LongBook (76 pages) (297mm X 210mm) | B13: Register | C13: 50 | D13: 35 | E13: =C13+D13-F13 -> 66 | F13: 19 | G13: 30 | H13: 42 | I13: =F13*H13 -> 798 | J13: =F13*G13 -> 570 | K13: =I13-J13 -> 228
... A65: Edet A4 White Sheets (150 gsm) | B65: A4 Sheets | C65: 67 | D65: 27 | E65: =C65+D65-F65 -> 65 | F65: 29 | G65: 2 | H65: 5 | I65: =F65*H65 -> 145 | J65: =F65*G65 -> 58 | K65: =I65-J65 -> 87

Sheet June
A1: Product Name | B1: Product Type | C1: Opening Stocks | D1: Purchases | E1: Closing Stock | F1: Units Sold | G1: Purchase Price | H1: Selling Price | I1: Total Revenue | J1: Total Cost | K1: Profit
A2: Classmate Pulse 6 subject spiral Notebook (300 pages) (240mm X 180mm) | B2: Spiral Notebook | C2: 63 | D2: 67 | E2: =C2+D2-F2 -> 68 | F2: 62 | G2: 90 | H2: 120 | I2: =F2*H2 -> 7440 | J2: =F2*G2 -> 5580 | K2: =I2-J2 -> 1860
A3: Classmate Pulse 6 subject spiral Notebook (300 pages) (267mm X 203mm) | B3: Spiral Notebook | C3: 56 | D3: 72 | E3: =C3+D3-F3 -> 76 | F3: 52 | G3: 135 | H3: 160 | I3: =F3*H3 -> 8320 | J3: =F3*G3 -> 7020 | K3: =I3-J3 -> 1300
A4: Classmate Pulse 6 subject spiral Notebook (300 pages) (297mm X 210mm) | B4: Spiral Notebook | C4: 74 | D4: 50 | E4: =C4+D4-F4 -> 75 | F4: 49 | G4: 165 | H4: 185 | I4: =F4*H4 -> 9065 | J4: =F4*G4 -> 8085 | K4: =I4-J4 -> 980
A5: Classmate Notebook Singleline Ruled (120 pages) (240mm X 180mm) | B5: Ruled Notebook | C5: 47 | D5: 63 | E5: =C5+D5-F5 -> 53 | F5: 57 | G5: 25 | H5: 35 | I5: =F5*H5 -> 1995 | J5: =F5*G5 -> 1425 | K5: =I5-J5 -> 570
A6: Classmate Notebook Singleline Ruled (172 pages) (272mm X 167mm) | B6: Ruled Notebook | C6: 60 | D6: 52 | E6: =C6+D6-F6 -> 66 | F6: 46 | G6: 30 | H6: 55 | I6: =F6*H6 -> 2530 | J6: =F6*G6 -> 1380 | K6: =I6-J6 -> 1150
A7: Navneet Notebook (92 pages) (180mm X 240mm) | B7: Ruled Notebook | C7: 56 | D7: 62 | E7: =C7+D7-F7 -> 51 | F7: 67 | G7: 18 | H7: 30 | I7: =F7*H7 -> 2010 | J7: =F7*G7 -> 1206 | K7: =I7-J7 -> 804
A8: Navneet Notebook (172 pages) (210mm X 297mm) | B8: Ruled Notebook | C8: 89 | D8: 65 | E8: =C8+D8-F8 -> 93 | F8: 61 | G8: 50 | H8: 65 | I8: =F8*H8 -> 3965 | J8: =F8*G8 -> 3050 | K8: =I8-J8 -> 915
A9: Classmate Notebook Unruled (168 pages) (240mm X 180mm) | B9: Unruled Notebook | C9: 51 | D9: 53 | E9: =C9+D9-F9 -> 62 | F9: 42 | G9: 35 | H9: 50 | I9: =F9*H9 -> 2100 | J9: =F9*G9 -> 1470 | K9: =I9-J9 -> 630
A10: Yuva Notebook Unruled (180 pages) (240mm X 180mm) | B10: Unruled Notebook | C10: 55 | D10: 48 | E10: =C10+D10-F10 -> 59 | F10: 44 | G10: 22 | H10: 40 | I10: =F10*H10 -> 1760 | J10: =F10*G10 -> 968 | K10: =I10-J10 -> 792
A11: Classmate LongBook (384 pages) (297mm X 210mm) | B11: Register | C11: 48 | D11: 37 | E11: =C11+D11-F11 -> 46 | F11: 39 | G11: 190 | H11: 220 | I11: =F11*H11 -> 8580 | J11: =F11*G11 -> 7410 | K11: =I11-J11 -> 1170
A12: Classmate LongBook (140 pages) (297mm X 210mm) | B12: Register | C12: 65 | D12: 45 | E12: =C12+D12-F12 -> 65 | F12: 45 | G12: 65 | H12: 85 | I12: =F12*H12 -> 3825 | J12: =F12*G12 -> 2925 | K12: =I12-J12 -> 900
A13: Navneet LongBook (76 pages) (297mm X 210mm) | B13: Register | C13: 66 | D13: 60 | E13: =C13+D13-F13 -> 56 | F13: 70 | G13: 30 | H13: 42 | I13: =F13*H13 -> 2940 | J13: =F13*G13 -> 2100 | K13: =I13-J13 -> 840
... A65: Edet A4 White Sheets (150 gsm) | B65: A4 Sheets | C65: 68 | D65: 27 | E65: =C65+D65-F65 -> 48 | F65: 47 | G65: 2 | H65: 5 | I65: =F65*H65 -> 235 | J65: =F65*G65 -> 94 | K65: =I65-J65 -> 141

Sheet Units Sold vs Units Purchased
A2: Product Type | B2: Units Sold | C2: Purchases
A3: {=_xlfn.UNIQUE(January!B2:B65)} -> Spiral Notebook | B3: 503 | C3: 595
A4: Ruled Notebook | B4: 705 | C4: 820 | L4: Product Type | M4: Units Sold | N4: Purchases
A5: Unruled Notebook | B5: 249 | C5: 310 | L5: Pencils | M5: 744 | N5: 802
A6: Register | B6: 413 | C6: 504 | L6: Pens | M6: 1313 | N6: 1408
A7: Pencils | B7: 744 | C7: 802 | L7: Spiral Notebook | M7: 503 | N7: 595
A8: Pens | B8: 1313 | C8: 1408 | L8: Ruled Notebook | M8: 705 | N8: 820
A9: Geometry Box | B9: 165 | C9: 163 | L9: Drawing Book | M9: 211 | N9: 359
A10: Chart Paper | B10: 266 | C10: 292 | L10: Markers | M10: 415 | N10: 600
A11: Adhesive | B11: 509 | C11: 575 | L11: Adhesive Tape | M11: 292 | N11: 390
A12: Color Pencils | B12: 416 | C12: 482 | L12: Geometry Box | M12: 165 | N12: 163
A13: Project File | B13: 228 | C13: 255 | L13: Stapler | M13: 208 | N13: 212
A14: Stapler | B14: 208 | C14: 212
A15: Drawing Book | B15: 211 | C15: 359
A16: Adhesive Tape | B16: 292 | C16: 390
A17: Markers | B17: 415 | C17: 600
A18: Water Colors and Oil paints | B18: 421 | C18: 592
A19: Notebook Cover | B19: 326 | C19: 458
A20: A4 Sheets | B20: 444 | C20: 488
A23: Units sold in each month
A24: Product Type | B24: January | C24: February | D24: March | E24: April | F24: May | G24: June | H24: Total
A25: {=_xlfn.UNIQUE(January!B2:B65)} -> Spiral Notebook | B25: =SUMIF(January!B2:B65,'Units Sold vs Units Purchased'!A25,January!F2:F4) -> 48 | C25: =SUMIF(February!B2:B65,'Units Sold vs Units Purchased'!A25,February!F2:F4) -> 31 | D25: =SUMIF(March!B2:B65,'Units Sold vs Units Purchased'!A25,March!F2:F4) -> 58 | E25: =SUMIF(April!B2:B65,'Units Sold vs Units Purchased'!A25,April!F2:F4) -> 131 | F25: =SUMIF(May!B2:B65,'Units Sold vs Units Purchased'!A25,May!F2:F4) -> 72 | G25: =SUMIF(June!B2:B65,'Units Sold vs Units Purchased'!A25,June!F2:F4) -> 163 | H25: =G25+F25+E25+D25+C25+B25 -> 503
A26: Ruled Notebook | B26: =SUMIF(January!B3:B66,'Units Sold vs Units Purchased'!A26,January!F3:F5) -> 63 | C26: =SUMIF(February!B3:B66,'Units Sold vs Units Purchased'!A26,February!F3:F5) -> 47 | D26: =SUMIF(March!B3:B66,'Units Sold vs Units Purchased'!A26,March!F3:F5) -> 78 | E26: =SUMIF(April!B3:B66,'Units Sold vs Units Purchased'!A26,April!F3:F5) -> 189 | F26: =SUMIF(May!B3:B66,'Units Sold vs Units Purchased'!A26,May!F3:F5) -> 97 | G26: =SUMIF(June!B3:B66,'Units Sold vs Units Purchased'!A26,June!F3:F5) -> 231 | H26: =G26+F26+E26+D26+C26+B26 -> 705
A27: Unruled Notebook | B27: =SUMIF(January!B4:B67,'Units Sold vs Units Purchased'!A27,January!F4:F6) -> 26 | C27: =SUMIF(February!B4:B67,'Units Sold vs Units Purchased'!A27,February!F4:F6) -> 13 | D27: =SUMIF(March!B4:B67,'Units Sold vs Units Purchased'!A27,March!F4:F6) -> 23 | E27: =SUMIF(April!B4:B67,'Units Sold vs Units Purchased'!A27,April!F4:F6) -> 65 | F27: =SUMIF(May!B4:B67,'Units Sold vs Units Purchased'!A27,May!F4:F6) -> 36 | G27: =SUMIF(June!B4:B67,'Units Sold vs Units Purchased'!A27,June!F4:F6) -> 86 | H27: =G27+F27+E27+D27+C27+B27 -> 249
A28: Register | B28: =SUMIF(January!B5:B68,'Units Sold vs Units Purchased'!A28,January!F5:F7) -> 31 | C28: =SUMIF(February!B5:B68,'Units Sold vs Units Purchased'!A28,February!F5:F7) -> 23 | D28: =SUMIF(March!B5:B68,'Units Sold vs Units Purchased'!A28,March!F5:F7) -> 46 | E28: =SUMIF(April!B5:B68,'Units Sold vs Units Purchased'!A28,April!F5:F7) -> 103 | F28: =SUMIF(May!B5:B68,'Units Sold vs Units Purchased'!A28,May!F5:F7) -> 56 | G28: =SUMIF(June!B5:B68,'Units Sold vs Units Purchased'!A28,June!F5:F7) -> 154 | H28: =G28+F28+E28+D28+C28+B28 -> 413
A29: Pencils | B29: =SUMIF(January!B6:B69,'Units Sold vs Units Purchased'!A29,January!F6:F8) -> 121 | C29: =SUMIF(February!B6:B69,'Units Sold vs Units Purchased'!A29,February!F6:F8) -> 84 | D29: =SUMIF(March!B6:B69,'Units Sold vs Units Purchased'!A29,March!F6:F8) -> 106 | E29: =SUMIF(April!B6:B69,'Units Sold vs Units Purchased'!A29,April!F6:F8) -> 154 | F29: =SUMIF(May!B6:B69,'Units Sold vs Units Purchased'!A29,May!F6:F8) -> 103 | G29: =SUMIF(June!B6:B69,'Units Sold vs Units Purchased'!A29,June!F6:F8) -> 176 | H29: =G29+F29+E29+D29+C29+B29 -> 744
A30: Pens | B30: =SUMIF(January!B7:B70,'Units Sold vs Units Purchased'!A30,January!F7:F9) -> 215 | C30: =SUMIF(February!B7:B70,'Units Sold vs Units Purchased'!A30,February!F7:F9) -> 168 | D30: =SUMIF(March!B7:B70,'Units Sold vs Units Purchased'!A30,March!F7:F9) -> 168 | E30: =SUMIF(April!B7:B70,'Units Sold vs Units Purchased'!A30,April!F7:F9) -> 250 | F30: =SUMIF(May!B7:B70,'Units Sold vs Units Purchased'!A30,May!F7:F9) -> 208 | G30: =SUMIF(June!B7:B70,'Units Sold vs Units Purchased'!A30,June!F7:F9) -> 304 | H30: =G30+F30+E30+D30+C30+B30 -> 1313
A31: Geometry Box | B31: =SUMIF(January!B8:B71,'Units Sold vs Units Purchased'!A31,January!F8:F10) -> 16 | C31: =SUMIF(February!B8:B71,'Units Sold vs Units Purchased'!A31,February!F8:F10) -> 8 | D31: =SUMIF(March!B8:B71,'Units Sold vs Units Purchased'!A31,March!F8:F10) -> 19 | E31: =SUMIF(April!B8:B71,'Units Sold vs Units Purchased'!A31,April!F8:F10) -> 42 | F31: =SUMIF(May!B8:B71,'Units Sold vs Units Purchased'!A31,May!F8:F10) -> 32 | G31: =SUMIF(June!B8:B71,'Units Sold vs Units Purchased'!A31,June!F8:F10) -> 48 | H31: =G31+F31+E31+D31+C31+B31 -> 165
A32: Chart Paper | B32: =SUMIF(January!B9:B72,'Units Sold vs Units Purchased'!A32,January!F9:F11) -> 24 | C32: =SUMIF(February!B9:B72,'Units Sold vs Units Purchased'!A32,February!F9:F11) -> 23 | D32: =SUMIF(March!B9:B72,'Units Sold vs Units Purchased'!A32,March!F9:F11) -> 29 | E32: =SUMIF(April!B9:B72,'Units Sold vs Units Purchased'!A32,April!F9:F11) -> 41 | F32: =SUMIF(May!B9:B72,'Units Sold vs Units Purchased'!A32,May!F9:F11) -> 58 | G32: =SUMIF(June!B9:B72,'Units Sold vs Units Purchased'!A32,June!F9:F11) -> 91 | H32: =G32+F32+E32+D32+C32+B32 -> 266
A33: Adhesive | B33: =SUMIF(January!B10:B73,'Units Sold vs Units Purchased'!A33,January!F10:F12) -> 80 | C33: =SUMIF(February!B10:B73,'Units Sold vs Units Purchased'!A33,February!F10:F12) -> 61 | D33: =SUMIF(March!B10:B73,'Units Sold vs Units Purchased'!A33,March!F10:F12) -> 66 | E33: =SUMIF(April!B10:B73,'Units Sold vs Units Purchased'!A33,April!F10:F12) -> 93 | F33: =SUMIF(May!B10:B73,'Units Sold vs Units Purchased'!A33,May!F10:F12) -> 87 | G33: =SUMIF(June!B10:B73,'Units Sold vs Units Purchased'!A33,June!F10:F12) -> 122 | H33: =G33+F33+E33+D33+C33+B33 -> 509
A34: Color Pencils | B34: =SUMIF(January!B11:B74,'Units Sold vs Units Purchased'!A34,January!F11:F13) -> 50 | C34: =SUMIF(February!B11:B74,'Units Sold vs Units Purchased'!A34,February!F11:F13) -> 35 | D34: =SUMIF(March!B11:B74,'Units Sold vs Units Purchased'!A34,March!F11:F13) -> 58 | E34: =SUMIF(April!B11:B74,'Units Sold vs Units Purchased'!A34,April!F11:F13) -> 89 | F34: =SUMIF(May!B11:B74,'Units Sold vs Units Purchased'!A34,May!F11:F13) -> 82 | G34: =SUMIF(June!B11:B74,'Units Sold vs Units Purchased'!A34,June!F11:F13) -> 102 | H34: =G34+F34+E34+D34+C34+B34 -> 416
A35: Project File | B35: =SUMIF(January!B12:B75,'Units Sold vs Units Purchased'!A35,January!F12:F14) -> 30 | C35: =SUMIF(February!B12:B75,'Units Sold vs Units Purchased'!A35,February!F12:F14) -> 22 | D35: =SUMIF(March!B12:B75,'Units Sold vs Units Purchased'!A35,March!F12:F14) -> 26 | E35: =SUMIF(April!B12:B75,'Units Sold vs Units Purchased'!A35,April!F12:F14) -> 42 | F35: =SUMIF(May!B12:B75,'Units Sold vs Units Purchased'!A35,May!F12:F14) -> 57 | G35: =SUMIF(June!B12:B75,'Units Sold vs Units Purchased'!A35,June!F12:F14) -> 51 | H35: =G35+F35+E35+D35+C35+B35 -> 228
A36: Stapler | B36: =SUMIF(January!B13:B76,'Units Sold vs Units Purchased'!A36,January!F13:F15) -> 30 | C36: =SUMIF(February!B13:B76,'Units Sold vs Units Purchased'!A36,February!F13:F15) -> 19 | D36: =SUMIF(March!B13:B76,'Units Sold vs Units Purchased'!A36,March!F13:F15) -> 29 | E36: =SUMIF(April!B13:B76,'Units Sold vs Units Purchased'!A36,April!F13:F15) -> 35 | F36: =SUMIF(May!B13:B76,'Units Sold vs Units Purchased'!A36,May!F13:F15) -> 36 | G36: =SUMIF(June!B13:B76,'Units Sold vs Units Purchased'!A36,June!F13:F15) -> 59 | H36: =G36+F36+E36+D36+C36+B36 -> 208
A37: Drawing Book | B37: =SUMIF(January!B14:B77,'Units Sold vs Units Purchased'!A37,January!F14:F16) -> 26 | C37: =SUMIF(February!B14:B77,'Units Sold vs Units Purchased'!A37,February!F14:F16) -> 15 | D37: =SUMIF(March!B14:B77,'Units Sold vs Units Purchased'!A37,March!F14:F16) -> 28 | E37: =SUMIF(April!B14:B77,'Units Sold vs Units Purchased'!A37,April!F14:F16) -> 47 | F37: =SUMIF(May!B14:B77,'Units Sold vs Units Purchased'!A37,May!F14:F16) -> 36 | G37: =SUMIF(June!B14:B77,'Units Sold vs Units Purchased'!A37,June!F14:F16) -> 59 | H37: =G37+F37+E37+D37+C37+B37 -> 211
... A42: A4 Sheets | B42: =SUMIF(January!B19:B82,'Units Sold vs Units Purchased'!A42,January!F19:F21) -> 54 | C42: =SUMIF(February!B19:B82,'Units Sold vs Units Purchased'!A42,February!F19:F21) -> 41 | D42: =SUMIF(March!B19:B82,'Units Sold vs Units Purchased'!A42,March!F19:F21) -> 55 | E42: =SUMIF(April!B19:B82,'Units Sold vs Units Purchased'!A42,April!F19:F21) -> 72 | F42: =SUMIF(May!B19:B82,'Units Sold vs Units Purchased'!A42,May!F19:F21) -> 93 | G42: =SUMIF(June!B19:B82,'Units Sold vs Units Purchased'!A42,June!F19:F21) -> 129 | H42: =G42+F42+E42+D42+C42+B42 -> 444
A44: Units purchased each month
A45: Product Type | B45: January | C45: February | D45: March | E45: April | F45: May | G45: June | H45: Total
A46: {=_xlfn.UNIQUE(January!B2:B65)} -> Spiral Notebook | B46: =SUMIF(January!B2:B65,'Units Sold vs Units Purchased'!A46,January!D2:D4) -> 54 | C46: =SUMIF(February!B2:B65,'Units Sold vs Units Purchased'!A46,February!D2:D4) -> 34 | D46: =SUMIF(March!B2:B65,'Units Sold vs Units Purchased'!A46,March!D2:D4) -> 65 | E46: =SUMIF(April!B2:B65,'Units Sold vs Units Purchased'!A46,April!D2:D4) -> 140 | F46: =SUMIF(May!B2:B65,'Units Sold vs Units Purchased'!A46,May!D2:D4) -> 113 | G46: =SUMIF(June!B2:B65,'Units Sold vs Units Purchased'!A46,June!D2:D4) -> 189 | H46: =G46+F46+E46+D46+C46+B46 -> 595
A47: Ruled Notebook | B47: =SUMIF(January!B3:B66,'Units Sold vs Units Purchased'!A47,January!D3:D5) -> 76 | C47: =SUMIF(February!B3:B66,'Units Sold vs Units Purchased'!A47,February!D3:D5) -> 59 | D47: =SUMIF(March!B3:B66,'Units Sold vs Units Purchased'!A47,March!D3:D5) -> 102 | E47: =SUMIF(April!B3:B66,'Units Sold vs Units Purchased'!A47,April!D3:D5) -> 192 | F47: =SUMIF(May!B3:B66,'Units Sold vs Units Purchased'!A47,May!D3:D5) -> 149 | G47: =SUMIF(June!B3:B66,'Units Sold vs Units Purchased'!A47,June!D3:D5) -> 242 | H47: =G47+F47+E47+D47+C47+B47 -> 820
A48: Unruled Notebook | B48: =SUMIF(January!B4:B67,'Units Sold vs Units Purchased'!A48,January!D4:D6) -> 26 | C48: =SUMIF(February!B4:B67,'Units Sold vs Units Purchased'!A48,February!D4:D6) -> 21 | D48: =SUMIF(March!B4:B67,'Units Sold vs Units Purchased'!A48,March!D4:D6) -> 26 | E48: =SUMIF(April!B4:B67,'Units Sold vs Units Purchased'!A48,April!D4:D6) -> 71 | F48: =SUMIF(May!B4:B67,'Units Sold vs Units Purchased'!A48,May!D4:D6) -> 65 | G48: =SUMIF(June!B4:B67,'Units Sold vs Units Purchased'!A48,June!D4:D6) -> 101 | H48: =G48+F48+E48+D48+C48+B48 -> 310
A49: Register | B49: =SUMIF(January!B5:B68,'Units Sold vs Units Purchased'!A49,January!D5:D7) -> 32 | C49: =SUMIF(February!B5:B68,'Units Sold vs Units Purchased'!A49,February!D5:D7) -> 60 | D49: =SUMIF(March!B5:B68,'Units Sold vs Units Purchased'!A49,March!D5:D7) -> 67 | E49: =SUMIF(April!B5:B68,'Units Sold vs Units Purchased'!A49,April!D5:D7) -> 113 | F49: =SUMIF(May!B5:B68,'Units Sold vs Units Purchased'!A49,May!D5:D7) -> 90 | G49: =SUMIF(June!B5:B68,'Units Sold vs Units Purchased'!A49,June!D5:D7) -> 142 | H49: =G49+F49+E49+D49+C49+B49 -> 504
A50: Pencils | B50: =SUMIF(January!B6:B69,'Units Sold vs Units Purchased'!A50,January!D6:D8) -> 67 | C50: =SUMIF(February!B6:B69,'Units Sold vs Units Purchased'!A50,February!D6:D8) -> 103 | D50: =SUMIF(March!B6:B69,'Units Sold vs Units Purchased'!A50,March!D6:D8) -> 110 | E50: =SUMIF(April!B6:B69,'Units Sold vs Units Purchased'!A50,April!D6:D8) -> 182 | F50: =SUMIF(May!B6:B69,'Units Sold vs Units Purchased'!A50,May!D6:D8) -> 173 | G50: =SUMIF(June!B6:B69,'Units Sold vs Units Purchased'!A50,June!D6:D8) -> 167 | H50: =G50+F50+E50+D50+C50+B50 -> 802
A51: Pens | B51: =SUMIF(January!B7:B70,'Units Sold vs Units Purchased'!A51,January!D7:D9) -> 166 | C51: =SUMIF(February!B7:B70,'Units Sold vs Units Purchased'!A51,February!D7:D9) -> 167 | D51: =SUMIF(March!B7:B70,'Units Sold vs Units Purchased'!A51,March!D7:D9) -> 184 | E51: =SUMIF(April!B7:B70,'Units Sold vs Units Purchased'!A51,April!D7:D9) -> 259 | F51: =SUMIF(May!B7:B70,'Units Sold vs Units Purchased'!A51,May!D7:D9) -> 320 | G51: =SUMIF(June!B7:B70,'Units Sold vs Units Purchased'!A51,June!D7:D9) -> 312 | H51: =G51+F51+E51+D51+C51+B51 -> 1408
A52: Geometry Box | B52: =SUMIF(January!B8:B71,'Units Sold vs Units Purchased'!A52,January!D8:D10) -> 29 | C52: =SUMIF(February!B8:B71,'Units Sold vs Units Purchased'!A52,February!D8:D10) -> 5 | D52: =SUMIF(March!B8:B71,'Units Sold vs Units Purchased'!A52,March!D8:D10) -> 9 | E52: =SUMIF(April!B8:B71,'Units Sold vs Units Purchased'!A52,April!D8:D10) -> 42 | F52: =SUMIF(May!B8:B71,'Units Sold vs Units Purchased'!A52,May!D8:D10) -> 35 | G52: =SUMIF(June!B8:B71,'Units Sold vs Units Purchased'!A52,June!D8:D10) -> 43 | H52: =G52+F52+E52+D52+C52+B52 -> 163
A53: Chart Paper | B53: =SUMIF(January!B9:B72,'Units Sold vs Units Purchased'!A53,January!D9:D11) -> 46 | C53: =SUMIF(February!B9:B72,'Units Sold vs Units Purchased'!A53,February!D9:D11) -> 25 | D53: =SUMIF(March!B9:B72,'Units Sold vs Units Purchased'!A53,March!D9:D11) -> 37 | E53: =SUMIF(April!B9:B72,'Units Sold vs Units Purchased'!A53,April!D9:D11) -> 50 | F53: =SUMIF(May!B9:B72,'Units Sold vs Units Purchased'!A53,May!D9:D11) -> 59 | G53: =SUMIF(June!B9:B72,'Units Sold vs Units Purchased'!A53,June!D9:D11) -> 75 | H53: =G53+F53+E53+D53+C53+B53 -> 292
A54: Adhesive | B54: =SUMIF(January!B10:B73,'Units Sold vs Units Purchased'!A54,January!D10:D12) -> 89 | C54: =SUMIF(February!B10:B73,'Units Sold vs Units Purchased'!A54,February!D10:D12) -> 37 | D54: =SUMIF(March!B10:B73,'Units Sold vs Units Purchased'!A54,March!D10:D12) -> 80 | E54: =SUMIF(April!B10:B73,'Units Sold vs Units Purchased'!A54,April!D10:D12) -> 104 | F54: =SUMIF(May!B10:B73,'Units Sold vs Units Purchased'!A54,May!D10:D12) -> 122 | G54: =SUMIF(June!B10:B73,'Units Sold vs Units Purchased'!A54,June!D10:D12) -> 143 | H54: =G54+F54+E54+D54+C54+B54 -> 575
A55: Color Pencils | B55: =SUMIF(January!B11:B74,'Units Sold vs Units Purchased'!A55,January!D11:D13) -> 43 | C55: =SUMIF(February!B11:B74,'Units Sold vs Units Purchased'!A55,February!D11:D13) -> 35 | D55: =SUMIF(March!B11:B74,'Units Sold vs Units Purchased'!A55,March!D11:D13) -> 71 | E55: =SUMIF(April!B11:B74,'Units Sold vs Units Purchased'!A55,April!D11:D13) -> 100 | F55: =SUMIF(May!B11:B74,'Units Sold vs Units Purchased'!A55,May!D11:D13) -> 123 | G55: =SUMIF(June!B11:B74,'Units Sold vs Units Purchased'!A55,June!D11:D13) -> 110 | H55: =G55+F55+E55+D55+C55+B55 -> 482
A56: Project File | B56: =SUMIF(January!B12:B75,'Units Sold vs Units Purchased'!A56,January!D12:D14) -> 22 | C56: =SUMIF(February!B12:B75,'Units Sold vs Units Purchased'!A56,February!D12:D14) -> 22 | D56: =SUMIF(March!B12:B75,'Units Sold vs Units Purchased'!A56,March!D12:D14) -> 31 | E56: =SUMIF(April!B12:B75,'Units Sold vs Units Purchased'!A56,April!D12:D14) -> 57 | F56: =SUMIF(May!B12:B75,'Units Sold vs Units Purchased'!A56,May!D12:D14) -> 59 | G56: =SUMIF(June!B12:B75,'Units Sold vs Units Purchased'!A56,June!D12:D14) -> 64 | H56: =G56+F56+E56+D56+C56+B56 -> 255
A57: Stapler | B57: =SUMIF(January!B13:B76,'Units Sold vs Units Purchased'!A57,January!D13:D15) -> 25 | C57: =SUMIF(February!B13:B76,'Units Sold vs Units Purchased'!A57,February!D13:D15) -> 26 | D57: =SUMIF(March!B13:B76,'Units Sold vs Units Purchased'!A57,March!D13:D15) -> 28 | E57: =SUMIF(April!B13:B76,'Units Sold vs Units Purchased'!A57,April!D13:D15) -> 47 | F57: =SUMIF(May!B13:B76,'Units Sold vs Units Purchased'!A57,May!D13:D15) -> 39 | G57: =SUMIF(June!B13:B76,'Units Sold vs Units Purchased'!A57,June!D13:D15) -> 47 | H57: =G57+F57+E57+D57+C57+B57 -> 212
A58: Drawing Book | B58: =SUMIF(January!B14:B77,'Units Sold vs Units Purchased'!A58,January!D14:D16) -> 29 | C58: =SUMIF(February!B14:B77,'Units Sold vs Units Purchased'!A58,February!D14:D16) -> 60 | D58: =SUMIF(March!B14:B77,'Units Sold vs Units Purchased'!A58,March!D14:D16) -> 36 | E58: =SUMIF(April!B14:B77,'Units Sold vs Units Purchased'!A58,April!D14:D16) -> 56 | F58: =SUMIF(May!B14:B77,'Units Sold vs Units Purchased'!A58,May!D14:D16) -> 71 | G58: =SUMIF(June!B14:B77,'Units Sold vs Units Purchased'!A58,June!D14:D16) -> 107 | H58: =G58+F58+E58+D58+C58+B58 -> 359
... A63: A4 Sheets | B63: =SUMIF(January!B19:B82,'Units Sold vs Units Purchased'!A63,January!D19:D21) -> 72 | C63: =SUMIF(February!B19:B82,'Units Sold vs Units Purchased'!A63,February!D19:D21) -> 71 | D63: =SUMIF(March!B19:B82,'Units Sold vs Units Purchased'!A63,March!D19:D21) -> 59 | E63: =SUMIF(April!B19:B82,'Units Sold vs Units Purchased'!A63,April!D19:D21) -> 87 | F63: =SUMIF(May!B19:B82,'Units Sold vs Units Purchased'!A63,May!D19:D21) -> 87 | G63: =SUMIF(June!B19:B82,'Units Sold vs Units Purchased'!A63,June!D19:D21) -> 112 | H63: =G63+F63+E63+D63+C63+B63 -> 488

Sheet Monthly purchase by category
A1: Monthly Purchase by Product Type
A2: Product type | B2: January | C2: February | D2: March | E2: April | F2: May | G2: June
A3: {=_xlfn.UNIQUE(January!B2:B65)} -> Spiral Notebook | B3: =SUMIF(January!B2:B65,'Monthly purchase by category'!A3,January!D2:D65) -> 54 | C3: =SUMIF(February!B2:B65,'Monthly purchase by category'!A3,February!D2:D65) -> 34 | D3: =SUMIF(March!B2:B65,'Monthly purchase by category'!A3,March!D2:D65) -> 65 | E3: =SUMIF(April!B2:B65,'Monthly purchase by category'!A3,April!D2:D65) -> 140 | F3: =SUMIF(May!B2:B65,'Monthly purchase by category'!A3,May!D2:D65) -> 113 | G3: =SUMIF(June!B2:B65,'Monthly purchase by category'!A3,June!D2:D65) -> 189
A4: Ruled Notebook | B4: =SUMIF(January!B3:B66,'Monthly purchase by category'!A4,January!D3:D66) -> 76 | C4: =SUMIF(February!B3:B66,'Monthly purchase by category'!A4,February!D3:D66) -> 59 | D4: =SUMIF(March!B3:B66,'Monthly purchase by category'!A4,March!D3:D66) -> 102 | E4: =SUMIF(April!B3:B66,'Monthly purchase by category'!A4,April!D3:D66) -> 192 | F4: =SUMIF(May!B3:B66,'Monthly purchase by category'!A4,May!D3:D66) -> 149 | G4: =SUMIF(June!B3:B66,'Monthly purchase by category'!A4,June!D3:D66) -> 242
A5: Unruled Notebook | B5: =SUMIF(January!B4:B67,'Monthly purchase by category'!A5,January!D4:D67) -> 26 | C5: =SUMIF(February!B4:B67,'Monthly purchase by category'!A5,February!D4:D67) -> 21 | D5: =SUMIF(March!B4:B67,'Monthly purchase by category'!A5,March!D4:D67) -> 26 | E5: =SUMIF(April!B4:B67,'Monthly purchase by category'!A5,April!D4:D67) -> 71 | F5: =SUMIF(May!B4:B67,'Monthly purchase by category'!A5,May!D4:D67) -> 65 | G5: =SUMIF(June!B4:B67,'Monthly purchase by category'!A5,June!D4:D67) -> 101
A6: Register | B6: =SUMIF(January!B5:B68,'Monthly purchase by category'!A6,January!D5:D68) -> 32 | C6: =SUMIF(February!B5:B68,'Monthly purchase by category'!A6,February!D5:D68) -> 60 | D6: =SUMIF(March!B5:B68,'Monthly purchase by category'!A6,March!D5:D68) -> 67 | E6: =SUMIF(April!B5:B68,'Monthly purchase by category'!A6,April!D5:D68) -> 113 | F6: =SUMIF(May!B5:B68,'Monthly purchase by category'!A6,May!D5:D68) -> 90 | G6: =SUMIF(June!B5:B68,'Monthly purchase by category'!A6,June!D5:D68) -> 142
A7: Pencils | B7: =SUMIF(January!B6:B69,'Monthly purchase by category'!A7,January!D6:D69) -> 67 | C7: =SUMIF(February!B6:B69,'Monthly purchase by category'!A7,February!D6:D69) -> 103 | D7: =SUMIF(March!B6:B69,'Monthly purchase by category'!A7,March!D6:D69) -> 110 | E7: =SUMIF(April!B6:B69,'Monthly purchase by category'!A7,April!D6:D69) -> 182 | F7: =SUMIF(May!B6:B69,'Monthly purchase by category'!A7,May!D6:D69) -> 173 | G7: =SUMIF(June!B6:B69,'Monthly purchase by category'!A7,June!D6:D69) -> 167
A8: Pens | B8: =SUMIF(January!B7:B70,'Monthly purchase by category'!A8,January!D7:D70) -> 166 | C8: =SUMIF(February!B7:B70,'Monthly purchase by category'!A8,February!D7:D70) -> 167 | D8: =SUMIF(March!B7:B70,'Monthly purchase by category'!A8,March!D7:D70) -> 184 | E8: =SUMIF(April!B7:B70,'Monthly purchase by category'!A8,April!D7:D70) -> 259 | F8: =SUMIF(May!B7:B70,'Monthly purchase by category'!A8,May!D7:D70) -> 320 | G8: =SUMIF(June!B7:B70,'Monthly purchase by category'!A8,June!D7:D70) -> 312
A9: Geometry Box | B9: =SUMIF(January!B8:B71,'Monthly purchase by category'!A9,January!D8:D71) -> 29 | C9: =SUMIF(February!B8:B71,'Monthly purchase by category'!A9,February!D8:D71) -> 5 | D9: =SUMIF(March!B8:B71,'Monthly purchase by category'!A9,March!D8:D71) -> 9 | E9: =SUMIF(April!B8:B71,'Monthly purchase by category'!A9,April!D8:D71) -> 42 | F9: =SUMIF(May!B8:B71,'Monthly purchase by category'!A9,May!D8:D71) -> 35 | G9: =SUMIF(June!B8:B71,'Monthly purchase by category'!A9,June!D8:D71) -> 43
A10: Chart Paper | B10: =SUMIF(January!B9:B72,'Monthly purchase by category'!A10,January!D9:D72) -> 46 | C10: =SUMIF(February!B9:B72,'Monthly purchase by category'!A10,February!D9:D72) -> 25 | D10: =SUMIF(March!B9:B72,'Monthly purchase by category'!A10,March!D9:D72) -> 37 | E10: =SUMIF(April!B9:B72,'Monthly purchase by category'!A10,April!D9:D72) -> 50 | F10: =SUMIF(May!B9:B72,'Monthly purchase by category'!A10,May!D9:D72) -> 59 | G10: =SUMIF(June!B9:B72,'Monthly purchase by category'!A10,June!D9:D72) -> 75
A11: Adhesive | B11: =SUMIF(January!B10:B73,'Monthly purchase by category'!A11,January!D10:D73) -> 89 | C11: =SUMIF(February!B10:B73,'Monthly purchase by category'!A11,February!D10:D73) -> 37 | D11: =SUMIF(March!B10:B73,'Monthly purchase by category'!A11,March!D10:D73) -> 80 | E11: =SUMIF(April!B10:B73,'Monthly purchase by category'!A11,April!D10:D73) -> 104 | F11: =SUMIF(May!B10:B73,'Monthly purchase by category'!A11,May!D10:D73) -> 122 | G11: =SUMIF(June!B10:B73,'Monthly purchase by category'!A11,June!D10:D73) -> 143
A12: Color Pencils | B12: =SUMIF(January!B11:B74,'Monthly purchase by category'!A12,January!D11:D74) -> 43 | C12: =SUMIF(February!B11:B74,'Monthly purchase by category'!A12,February!D11:D74) -> 35 | D12: =SUMIF(March!B11:B74,'Monthly purchase by category'!A12,March!D11:D74) -> 71 | E12: =SUMIF(April!B11:B74,'Monthly purchase by category'!A12,April!D11:D74) -> 100 | F12: =SUMIF(May!B11:B74,'Monthly purchase by category'!A12,May!D11:D74) -> 123 | G12: =SUMIF(June!B11:B74,'Monthly purchase by category'!A12,June!D11:D74) -> 110
A13: Project File | B13: =SUMIF(January!B12:B75,'Monthly purchase by category'!A13,January!D12:D75) -> 22 | C13: =SUMIF(February!B12:B75,'Monthly purchase by category'!A13,February!D12:D75) -> 22 | D13: =SUMIF(March!B12:B75,'Monthly purchase by category'!A13,March!D12:D75) -> 31 | E13: =SUMIF(April!B12:B75,'Monthly purchase by category'!A13,April!D12:D75) -> 57 | F13: =SUMIF(May!B12:B75,'Monthly purchase by category'!A13,May!D12:D75) -> 59 | G13: =SUMIF(June!B12:B75,'Monthly purchase by category'!A13,June!D12:D75) -> 64
A14: Stapler | B14: =SUMIF(January!B13:B76,'Monthly purchase by category'!A14,January!D13:D76) -> 25 | C14: =SUMIF(February!B13:B76,'Monthly purchase by category'!A14,February!D13:D76) -> 26 | D14: =SUMIF(March!B13:B76,'Monthly purchase by category'!A14,March!D13:D76) -> 28 | E14: =SUMIF(April!B13:B76,'Monthly purchase by category'!A14,April!D13:D76) -> 47 | F14: =SUMIF(May!B13:B76,'Monthly purchase by category'!A14,May!D13:D76) -> 39 | G14: =SUMIF(June!B13:B76,'Monthly purchase by category'!A14,June!D13:D76) -> 47
A15: Drawing Book | B15: =SUMIF(January!B14:B77,'Monthly purchase by category'!A15,January!D14:D77) -> 29 | C15: =SUMIF(February!B14:B77,'Monthly purchase by category'!A15,February!D14:D77) -> 60 | D15: =SUMIF(March!B14:B77,'Monthly purchase by category'!A15,March!D14:D77) -> 36 | E15: =SUMIF(April!B14:B77,'Monthly purchase by category'!A15,April!D14:D77) -> 56 | F15: =SUMIF(May!B14:B77,'Monthly purchase by category'!A15,May!D14:D77) -> 71 | G15: =SUMIF(June!B14:B77,'Monthly purchase by category'!A15,June!D14:D77) -> 107
... A20: A4 Sheets | B20: =SUMIF(January!B19:B82,'Monthly purchase by category'!A20,January!D19:D82) -> 72 | C20: =SUMIF(February!B19:B82,'Monthly purchase by category'!A20,February!D19:D82) -> 71 | D20: =SUMIF(March!B19:B82,'Monthly purchase by category'!A20,March!D19:D82) -> 59 | E20: =SUMIF(April!B19:B82,'Monthly purchase by category'!A20,April!D19:D82) -> 87 | F20: =SUMIF(May!B19:B82,'Monthly purchase by category'!A20,May!D19:D82) -> 87 | G20: =SUMIF(June!B19:B82,'Monthly purchase by category'!A20,June!D19:D82) -> 112
A24: Product Type | B24: January | C24: February | D24: March | E24: April | F24: May | G24: June
A25: Pens | B25: 166 | C25: 167 | D25: 184 | E25: 259 | F25: 320 | G25: 312
A26: Ruled Notebook | B26: 76 | C26: 59 | D26: 102 | E26: 192 | F26: 149 | G26: 242
A27: Project File | B27: 22 | C27: 22 | D27: 31 | E27: 57 | F27: 59 | G27: 64
A28: Markers | B28: 67 | C28: 64 | D28: 77 | E28: 109 | F28: 140 | G28: 143
A29: Color Pencils | B29: 43 | C29: 35 | D29: 71 | E29: 100 | F29: 123 | G29: 110
A30: Adhesive | B30: 89 | C30: 37 | D30: 80 | E30: 104 | F30: 122 | G30: 143
A38: Product Type | B38: January | C38: February | D38: March | E38: April | F38: May | G38: June
A39: Ruled Notebook | B39: 76 | C39: 59 | D39: 102 | E39: 192 | F39: 149 | G39: 242
A40: Water Colors and Oil paints | B40: 58 | C40: 82 | D40: 60 | E40: 133 | F40: 126 | G40: 133
A41: Spiral Notebook | B41: 54 | C41: 34 | D41: 65 | E41: 140 | F41: 113 | G41: 189

Sheet Monthly sales trends
A1: Monthly Sales Trends Category Wise
A2: Product Type | B2: January | C2: February | D2: March | E2: April | F2: May | G2: June
A3: Pens | B3: 215 | C3: 168 | D3: 168 | E3: 250 | F3: 208 | G3: 304
A4: Ruled Notebook | B4: 63 | C4: 47 | D4: 78 | E4: 189 | F4: 97 | G4: 231
A5: Spiral Notebook | B5: 48 | C5: 31 | D5: 58 | E5: 131 | F5: 72 | G5: 163
A6: A4 Sheets | B6: 54 | C6: 41 | D6: 55 | E6: 72 | F6: 93 | G6: 129
A7: Color Pencils | B7: 50 | C7: 35 | D7: 58 | E7: 89 | F7: 82 | G7: 102
A8: Adhesive | B8: 80 | C8: 61 | D8: 66 | E8: 93 | F8: 87 | G8: 122
A9: Water Colors | B9: 52 | C9: 27 | D9: 52 | E9: 90 | F9: 68 | G9: 132
A18: Month | B18: Units Sold | C18: Average
A19: January | B19: 998 | C19: 1304.67
A20: February | B20: 708 | C20: 1304.67
A21: March | B21: 972 | C21: 1304.67
A22: April | B22: 1651 | C22: 1304.67
A23: May | B23: 1298 | C23: 1304.67
A24: June | B24: 2201 | C24: 1304.67
A25: Avg. Sales | B25: =AVERAGE(B19,B20,B21,B22,B23,B24) -> 1304.6667

Sheet Top selling Products
A1: Top 5 Best-Selling Products (Units Sold, Monthly)
A2: Product Name | B2: January | C2: February | D2: March | E2: April | F2: May | G2: June
A3: Apsara Matt Magic 2.0 (10 pencils) | B3: 31 | C3: 25 | D3: 28 | E3: 39 | F3: 24 | G3: 48
A4: Cello Finegrip (10 pens) | B4: 32 | C4: 28 | D4: 32 | E4: 43 | F4: 33 | G4: 49
A5: Classmate Pulse 6 subject (300 pages) | B5: 18 | C5: 12 | D5: 23 | E5: 49 | F5: 27 | G5: 62
A6: Nataraj 621 Writing Pencils (10 pencils) | B6: 34 | C6: 17 | D6: 32 | E6: 44 | F6: 32 | G6: 49
A7: Pentonic 0.7mm (10 pens) | B7: 27 | C7: 18 | D7: 27 | E7: 41 | F7: 32 | G7: 41

Sheet Monthy closing stock
A2: Product Type | B2: January | C2: February | D2: March | E2: April | F2: May | G2: June
A3: {=_xlfn.UNIQUE(January!B2:B65)} -> Spiral Notebook | B3: =SUMIF(January!B2:B65,'Monthy closing stock'!A3,January!E2:E4) -> 139 | C3: =SUMIF(February!B2:B65,'Monthy closing stock'!A3,February!E2:E4) -> 138 | D3: =SUMIF(March!B2:B65,'Monthy closing stock'!A3,March!E2:E4) -> 146 | E3: =SUMIF(April!B2:B65,'Monthy closing stock'!A3,April!E2:E4) -> 155 | F3: =SUMIF(May!B2:B65,'Monthy closing stock'!A3,May!E2:E4) -> 196 | G3: =SUMIF(June!B2:B65,'Monthy closing stock'!A3,June!E2:E4) -> 219
A4: Ruled Notebook | B4: =SUMIF(January!B3:B66,'Monthy closing stock'!A4,January!E3:E5) -> 159 | C4: =SUMIF(February!B3:B66,'Monthy closing stock'!A4,February!E3:E5) -> 175 | D4: =SUMIF(March!B3:B66,'Monthy closing stock'!A4,March!E3:E5) -> 195 | E4: =SUMIF(April!B3:B66,'Monthy closing stock'!A4,April!E3:E5) -> 196 | F4: =SUMIF(May!B3:B66,'Monthy closing stock'!A4,May!E3:E5) -> 246 | G4: =SUMIF(June!B3:B66,'Monthy closing stock'!A4,June!E3:E5) -> 263
A5: Unruled Notebook | B5: =SUMIF(January!B4:B67,'Monthy closing stock'!A5,January!E4:E6) -> 64 | C5: =SUMIF(February!B4:B67,'Monthy closing stock'!A5,February!E4:E6) -> 71 | D5: =SUMIF(March!B4:B67,'Monthy closing stock'!A5,March!E4:E6) -> 73 | E5: =SUMIF(April!B4:B67,'Monthy closing stock'!A5,April!E4:E6) -> 83 | F5: =SUMIF(May!B4:B67,'Monthy closing stock'!A5,May!E4:E6) -> 111 | G5: =SUMIF(June!B4:B67,'Monthy closing stock'!A5,June!E4:E6) -> 121
A6: Register | B6: =SUMIF(January!B5:B68,'Monthy closing stock'!A6,January!E5:E7) -> 69 | C6: =SUMIF(February!B5:B68,'Monthy closing stock'!A6,February!E5:E7) -> 109 | D6: =SUMIF(March!B5:B68,'Monthy closing stock'!A6,March!E5:E7) -> 130 | E6: =SUMIF(April!B5:B68,'Monthy closing stock'!A6,April!E5:E7) -> 143 | F6: =SUMIF(May!B5:B68,'Monthy closing stock'!A6,May!E5:E7) -> 179 | G6: =SUMIF(June!B5:B68,'Monthy closing stock'!A6,June!E5:E7) -> 167
A7: Pencils | B7: =SUMIF(January!B6:B69,'Monthy closing stock'!A7,January!E6:E8) -> 148 | C7: =SUMIF(February!B6:B69,'Monthy closing stock'!A7,February!E6:E8) -> 175 | D7: =SUMIF(March!B6:B69,'Monthy closing stock'!A7,March!E6:E8) -> 176 | E7: =SUMIF(April!B6:B69,'Monthy closing stock'!A7,April!E6:E8) -> 204 | F7: =SUMIF(May!B6:B69,'Monthy closing stock'!A7,May!E6:E8) -> 272 | G7: =SUMIF(June!B6:B69,'Monthy closing stock'!A7,June!E6:E8) -> 265
A8: Pens | B8: =SUMIF(January!B7:B70,'Monthy closing stock'!A8,January!E7:E9) -> 307 | C8: =SUMIF(February!B7:B70,'Monthy closing stock'!A8,February!E7:E9) -> 310 | D8: =SUMIF(March!B7:B70,'Monthy closing stock'!A8,March!E7:E9) -> 334 | E8: =SUMIF(April!B7:B70,'Monthy closing stock'!A8,April!E7:E9) -> 349 | F8: =SUMIF(May!B7:B70,'Monthy closing stock'!A8,May!E7:E9) -> 457 | G8: =SUMIF(June!B7:B70,'Monthy closing stock'!A8,June!E7:E9) -> 465
A9: Geometry Box | B9: =SUMIF(January!B8:B71,'Monthy closing stock'!A9,January!E8:E10) -> 58 | C9: =SUMIF(February!B8:B71,'Monthy closing stock'!A9,February!E8:E10) -> 56 | D9: =SUMIF(March!B8:B71,'Monthy closing stock'!A9,March!E8:E10) -> 46 | E9: =SUMIF(April!B8:B71,'Monthy closing stock'!A9,April!E8:E10) -> 47 | F9: =SUMIF(May!B8:B71,'Monthy closing stock'!A9,May!E8:E10) -> 53 | G9: =SUMIF(June!B8:B71,'Monthy closing stock'!A9,June!E8:E10) -> 48
A10: Chart Paper | B10: =SUMIF(January!B9:B72,'Monthy closing stock'!A10,January!E9:E11) -> 71 | C10: =SUMIF(February!B9:B72,'Monthy closing stock'!A10,February!E9:E11) -> 72 | D10: =SUMIF(March!B9:B72,'Monthy closing stock'!A10,March!E9:E11) -> 80 | E10: =SUMIF(April!B9:B72,'Monthy closing stock'!A10,April!E9:E11) -> 87 | F10: =SUMIF(May!B9:B72,'Monthy closing stock'!A10,May!E9:E11) -> 88 | G10: =SUMIF(June!B9:B72,'Monthy closing stock'!A10,June!E9:E11) -> 73
A11: Adhesive | B11: =SUMIF(January!B10:B73,'Monthy closing stock'!A11,January!E10:E12) -> 175 | C11: =SUMIF(February!B10:B73,'Monthy closing stock'!A11,February!E10:E12) -> 152 | D11: =SUMIF(March!B10:B73,'Monthy closing stock'!A11,March!E10:E12) -> 164 | E11: =SUMIF(April!B10:B73,'Monthy closing stock'!A11,April!E10:E12) -> 180 | F11: =SUMIF(May!B10:B73,'Monthy closing stock'!A11,May!E10:E12) -> 212 | G11: =SUMIF(June!B10:B73,'Monthy closing stock'!A11,June!E10:E12) -> 231
A12: Color Pencils | B12: =SUMIF(January!B11:B74,'Monthy closing stock'!A12,January!E11:E13) -> 93 | C12: =SUMIF(February!B11:B74,'Monthy closing stock'!A12,February!E11:E13) -> 90 | D12: =SUMIF(March!B11:B74,'Monthy closing stock'!A12,March!E11:E13) -> 103 | E12: =SUMIF(April!B11:B74,'Monthy closing stock'!A12,April!E11:E13) -> 113 | F12: =SUMIF(May!B11:B74,'Monthy closing stock'!A12,May!E11:E13) -> 154 | G12: =SUMIF(June!B11:B74,'Monthy closing stock'!A12,June!E11:E13) -> 164
A13: Project File | B13: =SUMIF(January!B12:B75,'Monthy closing stock'!A13,January!E12:E14) -> 51 | C13: =SUMIF(February!B12:B75,'Monthy closing stock'!A13,February!E12:E14) -> 51 | D13: =SUMIF(March!B12:B75,'Monthy closing stock'!A13,March!E12:E14) -> 56 | E13: =SUMIF(April!B12:B75,'Monthy closing stock'!A13,April!E12:E14) -> 70 | F13: =SUMIF(May!B12:B75,'Monthy closing stock'!A13,May!E12:E14) -> 70 | G13: =SUMIF(June!B12:B75,'Monthy closing stock'!A13,June!E12:E14) -> 79
A14: Stapler | B14: =SUMIF(January!B13:B76,'Monthy closing stock'!A14,January!E13:E15) -> 54 | C14: =SUMIF(February!B13:B76,'Monthy closing stock'!A14,February!E13:E15) -> 61 | D14: =SUMIF(March!B13:B76,'Monthy closing stock'!A14,March!E13:E15) -> 59 | E14: =SUMIF(April!B13:B76,'Monthy closing stock'!A14,April!E13:E15) -> 73 | F14: =SUMIF(May!B13:B76,'Monthy closing stock'!A14,May!E13:E15) -> 74 | G14: =SUMIF(June!B13:B76,'Monthy closing stock'!A14,June!E13:E15) -> 63
A15: Drawing Book | B15: =SUMIF(January!B14:B77,'Monthy closing stock'!A15,January!E14:E16) -> 57 | C15: =SUMIF(February!B14:B77,'Monthy closing stock'!A15,February!E14:E16) -> 102 | D15: =SUMIF(March!B14:B77,'Monthy closing stock'!A15,March!E14:E16) -> 110 | E15: =SUMIF(April!B14:B77,'Monthy closing stock'!A15,April!E14:E16) -> 118 | F15: =SUMIF(May!B14:B77,'Monthy closing stock'!A15,May!E14:E16) -> 157 | G15: =SUMIF(June!B14:B77,'Monthy closing stock'!A15,June!E14:E16) -> 204
... A20: A4 Sheets | B20: =SUMIF(January!B19:B82,'Monthy closing stock'!A20,January!E19:E21) -> 130 | C20: =SUMIF(February!B19:B82,'Monthy closing stock'!A20,February!E19:E21) -> 163 | D20: =SUMIF(March!B19:B82,'Monthy closing stock'!A20,March!E19:E21) -> 171 | E20: =SUMIF(April!B19:B82,'Monthy closing stock'!A20,April!E19:E21) -> 187 | F20: =SUMIF(May!B19:B82,'Monthy closing stock'!A20,May!E19:E21) -> 184 | G20: =SUMIF(June!B19:B82,'Monthy closing stock'!A20,June!E19:E21) -> 170
A24: Product Type | B24: January | C24: February | D24: March | E24: April | F24: May | G24: June
A25: Pencils | B25: 148 | C25: 175 | D25: 176 | E25: 204 | F25: 272 | G25: 265
A26: Pens | B26: 307 | C26: 310 | D26: 334 | E26: 349 | F26: 457 | G26: 465
A27: Spiral Notebook | B27: 139 | C27: 138 | D27: 146 | E27: 155 | F27: 196 | G27: 219
A28: Ruled Notebook | B28: 159 | C28: 175 | D28: 195 | E28: 196 | F28: 246 | G28: 263
A29: Adhesive | B29: 175 | C29: 152 | D29: 164 | E29: 180 | F29: 212 | G29: 231
A30: Markers | B30: 119 | C30: 139 | D30: 160 | E30: 184 | F30: 253 | G30: 289

Sheet Cummulative sales
A1: Profit Table by Product Type
A2: Product Type | B2: January | C2: February | D2: March | E2: April | F2: May | G2: June
A3: {=_xlfn.UNIQUE(January!B2:B65)} -> Spiral Notebook | B3: =SUMIF(January!B2:B65,'Cummulative sales'!A3,January!F2:F4) -> 48 | C3: =SUMIF(February!B2:B65,'Cummulative sales'!A3,February!F2:F4) -> 31 | D3: =SUMIF(March!B2:B65,'Cummulative sales'!A3,March!F2:F4) -> 58 | E3: =SUMIF(April!B2:B65,'Cummulative sales'!A3,April!F2:F4) -> 131 | F3: =SUMIF(May!B2:B65,'Cummulative sales'!A3,May!F2:F4) -> 72 | G3: =SUMIF(June!B2:B65,'Cummulative sales'!A3,June!F2:F4) -> 163
A4: Ruled Notebook | B4: =SUMIF(January!B3:B66,'Cummulative sales'!A4,January!F3:F5) -> 63 | C4: =SUMIF(February!B3:B66,'Cummulative sales'!A4,February!F3:F5) -> 47 | D4: =SUMIF(March!B3:B66,'Cummulative sales'!A4,March!F3:F5) -> 78 | E4: =SUMIF(April!B3:B66,'Cummulative sales'!A4,April!F3:F5) -> 189 | F4: =SUMIF(May!B3:B66,'Cummulative sales'!A4,May!F3:F5) -> 97 | G4: =SUMIF(June!B3:B66,'Cummulative sales'!A4,June!F3:F5) -> 231
A5: Unruled Notebook | B5: =SUMIF(January!B4:B67,'Cummulative sales'!A5,January!F4:F6) -> 26 | C5: =SUMIF(February!B4:B67,'Cummulative sales'!A5,February!F4:F6) -> 13 | D5: =SUMIF(March!B4:B67,'Cummulative sales'!A5,March!F4:F6) -> 23 | E5: =SUMIF(April!B4:B67,'Cummulative sales'!A5,April!F4:F6) -> 65 | F5: =SUMIF(May!B4:B67,'Cummulative sales'!A5,May!F4:F6) -> 36 | G5: =SUMIF(June!B4:B67,'Cummulative sales'!A5,June!F4:F6) -> 86
A6: Register | B6: =SUMIF(January!B5:B68,'Cummulative sales'!A6,January!F5:F7) -> 31 | C6: =SUMIF(February!B5:B68,'Cummulative sales'!A6,February!F5:F7) -> 23 | D6: =SUMIF(March!B5:B68,'Cummulative sales'!A6,March!F5:F7) -> 46 | E6: =SUMIF(April!B5:B68,'Cummulative sales'!A6,April!F5:F7) -> 103 | F6: =SUMIF(May!B5:B68,'Cummulative sales'!A6,May!F5:F7) -> 56 | G6: =SUMIF(June!B5:B68,'Cummulative sales'!A6,June!F5:F7) -> 154
A7: Pencils | B7: =SUMIF(January!B6:B69,'Cummulative sales'!A7,January!F6:F8) -> 121 | C7: =SUMIF(February!B6:B69,'Cummulative sales'!A7,February!F6:F8) -> 84 | D7: =SUMIF(March!B6:B69,'Cummulative sales'!A7,March!F6:F8) -> 106 | E7: =SUMIF(April!B6:B69,'Cummulative sales'!A7,April!F6:F8) -> 154 | F7: =SUMIF(May!B6:B69,'Cummulative sales'!A7,May!F6:F8) -> 103 | G7: =SUMIF(June!B6:B69,'Cummulative sales'!A7,June!F6:F8) -> 176
A8: Pens | B8: =SUMIF(January!B7:B70,'Cummulative sales'!A8,January!F7:F9) -> 215 | C8: =SUMIF(February!B7:B70,'Cummulative sales'!A8,February!F7:F9) -> 168 | D8: =SUMIF(March!B7:B70,'Cummulative sales'!A8,March!F7:F9) -> 168 | E8: =SUMIF(April!B7:B70,'Cummulative sales'!A8,April!F7:F9) -> 250 | F8: =SUMIF(May!B7:B70,'Cummulative sales'!A8,May!F7:F9) -> 208 | G8: =SUMIF(June!B7:B70,'Cummulative sales'!A8,June!F7:F9) -> 304
A9: Geometry Box | B9: =SUMIF(January!B8:B71,'Cummulative sales'!A9,January!F8:F10) -> 16 | C9: =SUMIF(February!B8:B71,'Cummulative sales'!A9,February!F8:F10) -> 8 | D9: =SUMIF(March!B8:B71,'Cummulative sales'!A9,March!F8:F10) -> 19 | E9: =SUMIF(April!B8:B71,'Cummulative sales'!A9,April!F8:F10) -> 42 | F9: =SUMIF(May!B8:B71,'Cummulative sales'!A9,May!F8:F10) -> 32 | G9: =SUMIF(June!B8:B71,'Cummulative sales'!A9,June!F8:F10) -> 48
A10: Chart Paper | B10: =SUMIF(January!B9:B72,'Cummulative sales'!A10,January!F9:F11) -> 24 | C10: =SUMIF(February!B9:B72,'Cummulative sales'!A10,February!F9:F11) -> 23 | D10: =SUMIF(March!B9:B72,'Cummulative sales'!A10,March!F9:F11) -> 29 | E10: =SUMIF(April!B9:B72,'Cummulative sales'!A10,April!F9:F11) -> 41 | F10: =SUMIF(May!B9:B72,'Cummulative sales'!A10,May!F9:F11) -> 58 | G10: =SUMIF(June!B9:B72,'Cummulative sales'!A10,June!F9:F11) -> 91
A11: Adhesive | B11: =SUMIF(January!B10:B73,'Cummulative sales'!A11,January!F10:F12) -> 80 | C11: =SUMIF(February!B10:B73,'Cummulative sales'!A11,February!F10:F12) -> 61 | D11: =SUMIF(March!B10:B73,'Cummulative sales'!A11,March!F10:F12) -> 66 | E11: =SUMIF(April!B10:B73,'Cummulative sales'!A11,April!F10:F12) -> 93 | F11: =SUMIF(May!B10:B73,'Cummulative sales'!A11,May!F10:F12) -> 87 | G11: =SUMIF(June!B10:B73,'Cummulative sales'!A11,June!F10:F12) -> 122
A12: Color Pencils | B12: =SUMIF(January!B11:B74,'Cummulative sales'!A12,January!F11:F13) -> 50 | C12: =SUMIF(February!B11:B74,'Cummulative sales'!A12,February!F11:F13) -> 35 | D12: =SUMIF(March!B11:B74,'Cummulative sales'!A12,March!F11:F13) -> 58 | E12: =SUMIF(April!B11:B74,'Cummulative sales'!A12,April!F11:F13) -> 89 | F12: =SUMIF(May!B11:B74,'Cummulative sales'!A12,May!F11:F13) -> 82 | G12: =SUMIF(June!B11:B74,'Cummulative sales'!A12,June!F11:F13) -> 102
A13: Project File | B13: =SUMIF(January!B12:B75,'Cummulative sales'!A13,January!F12:F14) -> 30 | C13: =SUMIF(February!B12:B75,'Cummulative sales'!A13,February!F12:F14) -> 22 | D13: =SUMIF(March!B12:B75,'Cummulative sales'!A13,March!F12:F14) -> 26 | E13: =SUMIF(April!B12:B75,'Cummulative sales'!A13,April!F12:F14) -> 42 | F13: =SUMIF(May!B12:B75,'Cummulative sales'!A13,May!F12:F14) -> 57 | G13: =SUMIF(June!B12:B75,'Cummulative sales'!A13,June!F12:F14) -> 51
A14: Stapler | B14: =SUMIF(January!B13:B76,'Cummulative sales'!A14,January!F13:F15) -> 30 | C14: =SUMIF(February!B13:B76,'Cummulative sales'!A14,February!F13:F15) -> 19 | D14: =SUMIF(March!B13:B76,'Cummulative sales'!A14,March!F13:F15) -> 29 | E14: =SUMIF(April!B13:B76,'Cummulative sales'!A14,April!F13:F15) -> 35 | F14: =SUMIF(May!B13:B76,'Cummulative sales'!A14,May!F13:F15) -> 36 | G14: =SUMIF(June!B13:B76,'Cummulative sales'!A14,June!F13:F15) -> 59
A15: Drawing Book | B15: =SUMIF(January!B14:B77,'Cummulative sales'!A15,January!F14:F16) -> 26 | C15: =SUMIF(February!B14:B77,'Cummulative sales'!A15,February!F14:F16) -> 15 | D15: =SUMIF(March!B14:B77,'Cummulative sales'!A15,March!F14:F16) -> 28 | E15: =SUMIF(April!B14:B77,'Cummulative sales'!A15,April!F14:F16) -> 47 | F15: =SUMIF(May!B14:B77,'Cummulative sales'!A15,May!F14:F16) -> 36 | G15: =SUMIF(June!B14:B77,'Cummulative sales'!A15,June!F14:F16) -> 59
... A20: A4 Sheets | B20: =SUMIF(January!B19:B82,'Cummulative sales'!A20,January!F19:F21) -> 54 | C20: =SUMIF(February!B19:B82,'Cummulative sales'!A20,February!F19:F21) -> 41 | D20: =SUMIF(March!B19:B82,'Cummulative sales'!A20,March!F19:F21) -> 55 | E20: =SUMIF(April!B19:B82,'Cummulative sales'!A20,April!F19:F21) -> 72 | F20: =SUMIF(May!B19:B82,'Cummulative sales'!A20,May!F19:F21) -> 93 | G20: =SUMIF(June!B19:B82,'Cummulative sales'!A20,June!F19:F21) -> 129
A24: Cummulative Units sold
A25: Product Type | B25: January | C25: February | D25: March | E25: April | F25: May | G25: June | I25: Product Type | J25: January | K25: February | L25: March | M25: April | N25: May | O25: June
A26: {=_xlfn.UNIQUE(January!B2:B65)} -> Spiral Notebook | B26: 48 | C26: =B26+C3 -> 79 | D26: =B26+C26+D3 -> 185 | E26: =B26+C26+D26+E3 -> 443 | F26: =B26+C26+D26+E26+F3 -> 827 | G26: =B26+C26+D26+E26+F26+G3 -> 1745 | I26: A4 Sheets | J26: 54 | K26: 95 | L26: 150 | M26: 222 | N26: 315 | O26: 444
A27: Ruled Notebook | B27: 63 | C27: =B27+C4 -> 110 | D27: =B27+C27+D4 -> 251 | E27: =B27+C27+D27+E4 -> 613 | F27: =B27+C27+D27+E27+F4 -> 1134 | G27: =B27+C27+D27+E27+F27+G4 -> 2402 | I27: Adhesive | J27: 80 | K27: 141 | L27: 207 | M27: 300 | N27: 387 | O27: 509
A28: Unruled Notebook | B28: 26 | C28: =B28+C5 -> 39 | D28: =B28+C28+D5 -> 88 | E28: =B28+C28+D28+E5 -> 218 | F28: =B28+C28+D28+E28+F5 -> 407 | G28: =B28+C28+D28+E28+F28+G5 -> 864 | I28: Adhesive Tape | J28: 34 | K28: 61 | L28: 94 | M28: 149 | N28: 206 | O28: 292
A29: Register | B29: 31 | C29: =B29+C6 -> 54 | D29: =B29+C29+D6 -> 131 | E29: =B29+C29+D29+E6 -> 319 | F29: =B29+C29+D29+E29+F6 -> 591 | G29: =B29+C29+D29+E29+F29+G6 -> 1280 | I29: Chart Paper | J29: 24 | K29: 47 | L29: 76 | M29: 117 | N29: 175 | O29: 266
A30: Pencils | B30: 121 | C30: =B30+C7 -> 205 | D30: =B30+C30+D7 -> 432 | E30: =B30+C30+D30+E7 -> 912 | F30: =B30+C30+D30+E30+F7 -> 1773 | G30: =B30+C30+D30+E30+F30+G7 -> 3619 | I30: Color Pencils | J30: 50 | K30: 85 | L30: 143 | M30: 232 | N30: 314 | O30: 416
A31: Pens | B31: 215 | C31: =B31+C8 -> 383 | D31: =B31+C31+D8 -> 766 | E31: =B31+C31+D31+E8 -> 1614 | F31: =B31+C31+D31+E31+F8 -> 3186 | G31: =B31+C31+D31+E31+F31+G8 -> 6468 | I31: Drawing Book | J31: 26 | K31: 41 | L31: 69 | M31: 116 | N31: 152 | O31: 211
A32: Geometry Box | B32: 16 | C32: =B32+C9 -> 24 | D32: =B32+C32+D9 -> 59 | E32: =B32+C32+D32+E9 -> 141 | F32: =B32+C32+D32+E32+F9 -> 272 | G32: =B32+C32+D32+E32+F32+G9 -> 560 | I32: Geometry Box | J32: 16 | K32: 24 | L32: 43 | M32: 85 | N32: 117 | O32: 165
A33: Chart Paper | B33: 24 | C33: =B33+C10 -> 47 | D33: =B33+C33+D10 -> 100 | E33: =B33+C33+D33+E10 -> 212 | F33: =B33+C33+D33+E33+F10 -> 441 | G33: =B33+C33+D33+E33+F33+G10 -> 915 | I33: Markers | J33: 59 | K33: 101 | L33: 153 | M33: 241 | N33: 313 | O33: 415
A34: Adhesive | B34: 80 | C34: =B34+C11 -> 141 | D34: =B34+C34+D11 -> 287 | E34: =B34+C34+D34+E11 -> 601 | F34: =B34+C34+D34+E34+F11 -> 1196 | G34: =B34+C34+D34+E34+F34+G11 -> 2427 | I34: Notebook Cover | J34: 39 | K34: 61 | L34: 107 | M34: 172 | N34: 220 | O34: 326
A35: Color Pencils | B35: 50 | C35: =B35+C12 -> 85 | D35: =B35+C35+D12 -> 193 | E35: =B35+C35+D35+E12 -> 417 | F35: =B35+C35+D35+E35+F12 -> 827 | G35: =B35+C35+D35+E35+F35+G12 -> 1674 | I35: Pencils | J35: 121 | K35: 205 | L35: 311 | M35: 465 | N35: 568 | O35: 744
A36: Project File | B36: 30 | C36: =B36+C13 -> 52 | D36: =B36+C36+D13 -> 108 | E36: =B36+C36+D36+E13 -> 232 | F36: =B36+C36+D36+E36+F13 -> 479 | G36: =B36+C36+D36+E36+F36+G13 -> 952 | I36: Pens | J36: 215 | K36: 383 | L36: 551 | M36: 801 | N36: 1009 | O36: 1313
A37: Stapler | B37: 30 | C37: =B37+C14 -> 49 | D37: =B37+C37+D14 -> 108 | E37: =B37+C37+D37+E14 -> 222 | F37: =B37+C37+D37+E37+F14 -> 445 | G37: =B37+C37+D37+E37+F37+G14 -> 913 | I37: Project File | J37: 30 | K37: 52 | L37: 78 | M37: 120 | N37: 177 | O37: 228
A38: Drawing Book | B38: 26 | C38: =B38+C15 -> 41 | D38: =B38+C38+D15 -> 95 | E38: =B38+C38+D38+E15 -> 209 | F38: =B38+C38+D38+E38+F15 -> 407 | G38: =B38+C38+D38+E38+F38+G15 -> 837 | I38: Register | J38: 31 | K38: 54 | L38: 100 | M38: 203 | N38: 259 | O38: 413
... A43: A4 Sheets | B43: 54 | C43: =B43+C20 -> 95 | D43: =B43+C43+D20 -> 204 | E43: =B43+C43+D43+E20 -> 425 | F43: =B43+C43+D43+E43+F20 -> 871 | G43: =B43+C43+D43+E43+F43+G20 -> 1778 | I43: Water Colors and Oil paints | J43: 52 | K43: 79 | L43: 131 | M43: 221 | N43: 289 | O43: 421

Sheet Average Profit Margin
A1: Revenu Table by Product Type | M1: Cost Table by Product Type | W1: Profit table by Product Type
A2: Product Type | B2: January | C2: February | D2: March | E2: April | F2: May | G2: June | H2: Total | M2: Product Type | N2: January | O2: February | P2: March | Q2: April | R2: May | S2: June | T2: Total | W2: Product Type | X2: January | Y2: February | Z2: March | AA2: April | AB2: May | AC2: June | AD2: Total
A3: {=_xlfn.UNIQUE(January!B2:B65)} -> Spiral Notebook | B3: =SUMIF(January!B2:B65,'Average Profit Margin'!A3,January!I2:I4) -> 7360 | C3: =SUMIF(February!B2:B65,'Average Profit Margin'!A3,February!I2:I4) -> 4730 | D3: =SUMIF(March!B2:B65,'Average Profit Margin'!A3,March!I2:I4) -> 8785 | E3: =SUMIF(April!B2:B65,'Average Profit Margin'!A3,April!I2:I4) -> 19925 | F3: =SUMIF(May!B2:B65,'Average Profit Margin'!A3,May!I2:I4) -> 11015 | G3: =SUMIF(June!B2:B65,'Average Profit Margin'!A3,June!I2:I4) -> 24825 | H3: =B3+C3+D3+E3+F3+G3 -> 76640 | M3: {=_xlfn.UNIQUE(January!B2:B65)} -> Spiral Notebook | N3: =SUMIF(January!B2:B65,'Average Profit Margin'!M3,January!J2:J4) -> 6150 | O3: =SUMIF(February!B2:B65,'Average Profit Margin'!M3,February!J2:J4) -> 3945 | P3: =SUMIF(March!B2:B65,'Average Profit Margin'!M3,March!J2:J4) -> 7305 | Q3: =SUMIF(April!B2:B65,'Average Profit Margin'!M3,April!J2:J4) -> 16590 | R3: =SUMIF(May!B2:B65,'Average Profit Margin'!M3,May!J2:J4) -> 9195 | S3: =SUMIF(June!B2:B65,'Average Profit Margin'!M3,June!J2:J4) -> 20685 | T3: =N3+O3+P3+Q3+R3+S3 -> 63870 | W3: {=_xlfn.UNIQUE(January!B2:B65)} -> Spiral Notebook | X3: =SUMIF(January!B2:B65,'Average Profit Margin'!W3,January!K2:K4) -> 1210 | Y3: =SUMIF(February!B2:B65,'Average Profit Margin'!W3,February!K2:K4) -> 785 | Z3: =SUMIF(March!B2:B65,'Average Profit Margin'!W3,March!K2:K4) -> 1480 | AA3: =SUMIF(April!B2:B65,'Average Profit Margin'!W3,April!K2:K4) -> 3335 | AB3: =SUMIF(May!B2:B65,'Average Profit Margin'!W3,May!K2:K4) -> 1820 | AC3: =SUMIF(June!B2:B65,'Average Profit Margin'!W3,June!K2:K4) -> 4140 | AD3: =X3+Y3+Z3+AA3+AB3+AC3 -> 12770
A4: Ruled Notebook | B4: =SUMIF(January!B3:B66,'Average Profit Margin'!A4,January!I3:I5) -> 3035 | C4: =SUMIF(February!B3:B66,'Average Profit Margin'!A4,February!I3:I5) -> 2250 | D4: =SUMIF(March!B3:B66,'Average Profit Margin'!A4,March!I3:I5) -> 3520 | E4: =SUMIF(April!B3:B66,'Average Profit Margin'!A4,April!I3:I5) -> 8905 | F4: =SUMIF(May!B3:B66,'Average Profit Margin'!A4,May!I3:I5) -> 4480 | G4: =SUMIF(June!B3:B66,'Average Profit Margin'!A4,June!I3:I5) -> 10500 | H4: =B4+C4+D4+E4+F4+G4 -> 32690 | M4: Ruled Notebook | N4: =SUMIF(January!B3:B66,'Average Profit Margin'!M4,January!J3:J5) -> 2011 | O4: =SUMIF(February!B3:B66,'Average Profit Margin'!M4,February!J3:J5) -> 1502 | P4: =SUMIF(March!B3:B66,'Average Profit Margin'!M4,March!J3:J5) -> 2266 | Q4: =SUMIF(April!B3:B66,'Average Profit Margin'!M4,April!J3:J5) -> 5949 | R4: =SUMIF(May!B3:B66,'Average Profit Margin'!M4,May!J3:J5) -> 2961 | S4: =SUMIF(June!B3:B66,'Average Profit Margin'!M4,June!J3:J5) -> 7061 | T4: =N4+O4+P4+Q4+R4+S4 -> 21750 | W4: Ruled Notebook | X4: =SUMIF(January!B3:B66,'Average Profit Margin'!W4,January!K3:K5) -> 1024 | Y4: =SUMIF(February!B3:B66,'Average Profit Margin'!W4,February!K3:K5) -> 748 | Z4: =SUMIF(March!B3:B66,'Average Profit Margin'!W4,March!K3:K5) -> 1254 | AA4: =SUMIF(April!B3:B66,'Average Profit Margin'!W4,April!K3:K5) -> 2956 | AB4: =SUMIF(May!B3:B66,'Average Profit Margin'!W4,May!K3:K5) -> 1519 | AC4: =SUMIF(June!B3:B66,'Average Profit Margin'!W4,June!K3:K5) -> 3439 | AD4: =X4+Y4+Z4+AA4+AB4+AC4 -> 10940
A5: Unruled Notebook | B5: =SUMIF(January!B4:B67,'Average Profit Margin'!A5,January!I4:I6) -> 1170 | C5: =SUMIF(February!B4:B67,'Average Profit Margin'!A5,February!I4:I6) -> 590 | D5: =SUMIF(March!B4:B67,'Average Profit Margin'!A5,March!I4:I6) -> 1040 | E5: =SUMIF(April!B4:B67,'Average Profit Margin'!A5,April!I4:I6) -> 2910 | F5: =SUMIF(May!B4:B67,'Average Profit Margin'!A5,May!I4:I6) -> 1630 | G5: =SUMIF(June!B4:B67,'Average Profit Margin'!A5,June!I4:I6) -> 3860 | H5: =B5+C5+D5+E5+F5+G5 -> 11200 | M5: Unruled Notebook | N5: =SUMIF(January!B4:B67,'Average Profit Margin'!M5,January!J4:J6) -> 741 | O5: =SUMIF(February!B4:B67,'Average Profit Margin'!M5,February!J4:J6) -> 377 | P5: =SUMIF(March!B4:B67,'Average Profit Margin'!M5,March!J4:J6) -> 662 | Q5: =SUMIF(April!B4:B67,'Average Profit Margin'!M5,April!J4:J6) -> 1833 | R5: =SUMIF(May!B4:B67,'Average Profit Margin'!M5,May!J4:J6) -> 1039 | S5: =SUMIF(June!B4:B67,'Average Profit Margin'!M5,June!J4:J6) -> 2438 | T5: =N5+O5+P5+Q5+R5+S5 -> 7090 | W5: Unruled Notebook | X5: =SUMIF(January!B4:B67,'Average Profit Margin'!W5,January!K4:K6) -> 429 | Y5: =SUMIF(February!B4:B67,'Average Profit Margin'!W5,February!K4:K6) -> 213 | Z5: =SUMIF(March!B4:B67,'Average Profit Margin'!W5,March!K4:K6) -> 378 | AA5: =SUMIF(April!B4:B67,'Average Profit Margin'!W5,April!K4:K6) -> 1077 | AB5: =SUMIF(May!B4:B67,'Average Profit Margin'!W5,May!K4:K6) -> 591 | AC5: =SUMIF(June!B4:B67,'Average Profit Margin'!W5,June!K4:K6) -> 1422 | AD5: =X5+Y5+Z5+AA5+AB5+AC5 -> 4110
A6: Register | B6: =SUMIF(January!B5:B68,'Average Profit Margin'!A6,January!I5:I7) -> 3598 | C6: =SUMIF(February!B5:B68,'Average Profit Margin'!A6,February!I5:I7) -> 3090 | D6: =SUMIF(March!B5:B68,'Average Profit Margin'!A6,March!I5:I7) -> 5069 | E6: =SUMIF(April!B5:B68,'Average Profit Margin'!A6,April!I5:I7) -> 11091 | F6: =SUMIF(May!B5:B68,'Average Profit Margin'!A6,May!I5:I7) -> 5833 | G6: =SUMIF(June!B5:B68,'Average Profit Margin'!A6,June!I5:I7) -> 15345 | H6: =B6+C6+D6+E6+F6+G6 -> 44026 | M6: Register | N6: =SUMIF(January!B5:B68,'Average Profit Margin'!M6,January!J5:J7) -> 2950 | O6: =SUMIF(February!B5:B68,'Average Profit Margin'!M6,February!J5:J7) -> 2570 | P6: =SUMIF(March!B5:B68,'Average Profit Margin'!M6,March!J5:J7) -> 4145 | Q6: =SUMIF(April!B5:B68,'Average Profit Margin'!M6,April!J5:J7) -> 9065 | R6: =SUMIF(May!B5:B68,'Average Profit Margin'!M6,May!J5:J7) -> 4725 | S6: =SUMIF(June!B5:B68,'Average Profit Margin'!M6,June!J5:J7) -> 12435 | T6: =N6+O6+P6+Q6+R6+S6 -> 35890 | W6: Register | X6: =SUMIF(January!B5:B68,'Average Profit Margin'!W6,January!K5:K7) -> 648 | Y6: =SUMIF(February!B5:B68,'Average Profit Margin'!W6,February!K5:K7) -> 520 | Z6: =SUMIF(March!B5:B68,'Average Profit Margin'!W6,March!K5:K7) -> 924 | AA6: =SUMIF(April!B5:B68,'Average Profit Margin'!W6,April!K5:K7) -> 2026 | AB6: =SUMIF(May!B5:B68,'Average Profit Margin'!W6,May!K5:K7) -> 1108 | AC6: =SUMIF(June!B5:B68,'Average Profit Margin'!W6,June!K5:K7) -> 2910 | AD6: =X6+Y6+Z6+AA6+AB6+AC6 -> 8136
A7: Pencils | B7: =SUMIF(January!B6:B69,'Average Profit Margin'!A7,January!I6:I8) -> 7120 | C7: =SUMIF(February!B6:B69,'Average Profit Margin'!A7,February!I6:I8) -> 5100 | D7: =SUMIF(March!B6:B69,'Average Profit Margin'!A7,March!I6:I8) -> 6140 | E7: =SUMIF(April!B6:B69,'Average Profit Margin'!A7,April!I6:I8) -> 9060 | F7: =SUMIF(May!B6:B69,'Average Profit Margin'!A7,May!I6:I8) -> 5940 | G7: =SUMIF(June!B6:B69,'Average Profit Margin'!A7,June!I6:I8) -> 10320 | H7: =B7+C7+D7+E7+F7+G7 -> 43680 | M7: Pencils | N7: =SUMIF(January!B6:B69,'Average Profit Margin'!M7,January!J6:J8) -> 5150 | O7: =SUMIF(February!B6:B69,'Average Profit Margin'!M7,February!J6:J8) -> 3715 | P7: =SUMIF(March!B6:B69,'Average Profit Margin'!M7,March!J6:J8) -> 4410 | Q7: =SUMIF(April!B6:B69,'Average Profit Margin'!M7,April!J6:J8) -> 6555 | R7: =SUMIF(May!B6:B69,'Average Profit Margin'!M7,May!J6:J8) -> 4275 | S7: =SUMIF(June!B6:B69,'Average Profit Margin'!M7,June!J6:J8) -> 7440 | T7: =N7+O7+P7+Q7+R7+S7 -> 31545 | W7: Pencils | X7: =SUMIF(January!B6:B69,'Average Profit Margin'!W7,January!K6:K8) -> 1970 | Y7: =SUMIF(February!B6:B69,'Average Profit Margin'!W7,February!K6:K8) -> 1385 | Z7: =SUMIF(March!B6:B69,'Average Profit Margin'!W7,March!K6:K8) -> 1730 | AA7: =SUMIF(April!B6:B69,'Average Profit Margin'!W7,April!K6:K8) -> 2505 | AB7: =SUMIF(May!B6:B69,'Average Profit Margin'!W7,May!K6:K8) -> 1665 | AC7: =SUMIF(June!B6:B69,'Average Profit Margin'!W7,June!K6:K8) -> 2880 | AD7: =X7+Y7+Z7+AA7+AB7+AC7 -> 12135
A8: Pens | B8: =SUMIF(January!B7:B70,'Average Profit Margin'!A8,January!I7:I9) -> 17120 | C8: =SUMIF(February!B7:B70,'Average Profit Margin'!A8,February!I7:I9) -> 13350 | D8: =SUMIF(March!B7:B70,'Average Profit Margin'!A8,March!I7:I9) -> 13480 | E8: =SUMIF(April!B7:B70,'Average Profit Margin'!A8,April!I7:I9) -> 20010 | F8: =SUMIF(May!B7:B70,'Average Profit Margin'!A8,May!I7:I9) -> 16780 | G8: =SUMIF(June!B7:B70,'Average Profit Margin'!A8,June!I7:I9) -> 24530 | H8: =B8+C8+D8+E8+F8+G8 -> 105270 | M8: Pens | N8: =SUMIF(January!B7:B70,'Average Profit Margin'!M8,January!J7:J9) -> 13270 | O8: =SUMIF(February!B7:B70,'Average Profit Margin'!M8,February!J7:J9) -> 10360 | P8: =SUMIF(March!B7:B70,'Average Profit Margin'!M8,March!J7:J9) -> 10505 | Q8: =SUMIF(April!B7:B70,'Average Profit Margin'!M8,April!J7:J9) -> 15555 | R8: =SUMIF(May!B7:B70,'Average Profit Margin'!M8,May!J7:J9) -> 13090 | S8: =SUMIF(June!B7:B70,'Average Profit Margin'!M8,June!J7:J9) -> 19095 | T8: =N8+O8+P8+Q8+R8+S8 -> 81875 | W8: Pens | X8: =SUMIF(January!B7:B70,'Average Profit Margin'!W8,January!K7:K9) -> 3850 | Y8: =SUMIF(February!B7:B70,'Average Profit Margin'!W8,February!K7:K9) -> 2990 | Z8: =SUMIF(March!B7:B70,'Average Profit Margin'!W8,March!K7:K9) -> 2975 | AA8: =SUMIF(April!B7:B70,'Average Profit Margin'!W8,April!K7:K9) -> 4455 | AB8: =SUMIF(May!B7:B70,'Average Profit Margin'!W8,May!K7:K9) -> 3690 | AC8: =SUMIF(June!B7:B70,'Average Profit Margin'!W8,June!K7:K9) -> 5435 | AD8: =X8+Y8+Z8+AA8+AB8+AC8 -> 23395
A9: Geometry Box | B9: =SUMIF(January!B8:B71,'Average Profit Margin'!A9,January!I8:I10) -> 3270 | C9: =SUMIF(February!B8:B71,'Average Profit Margin'!A9,February!I8:I10) -> 1615 | D9: =SUMIF(March!B8:B71,'Average Profit Margin'!A9,March!I8:I10) -> 3975 | E9: =SUMIF(April!B8:B71,'Average Profit Margin'!A9,April!I8:I10) -> 8900 | F9: =SUMIF(May!B8:B71,'Average Profit Margin'!A9,May!I8:I10) -> 6595 | G9: =SUMIF(June!B8:B71,'Average Profit Margin'!A9,June!I8:I10) -> 9160 | H9: =B9+C9+D9+E9+F9+G9 -> 33515 | M9: Geometry Box | N9: =SUMIF(January!B8:B71,'Average Profit Margin'!M9,January!J8:J10) -> 2745 | O9: =SUMIF(February!B8:B71,'Average Profit Margin'!M9,February!J8:J10) -> 1340 | P9: =SUMIF(March!B8:B71,'Average Profit Margin'!M9,March!J8:J10) -> 3300 | Q9: =SUMIF(April!B8:B71,'Average Profit Margin'!M9,April!J8:J10) -> 7375 | R9: =SUMIF(May!B8:B71,'Average Profit Margin'!M9,May!J8:J10) -> 5495 | S9: =SUMIF(June!B8:B71,'Average Profit Margin'!M9,June!J8:J10) -> 7685 | T9: =N9+O9+P9+Q9+R9+S9 -> 27940 | W9: Geometry Box | X9: =SUMIF(January!B8:B71,'Average Profit Margin'!W9,January!K8:K10) -> 525 | Y9: =SUMIF(February!B8:B71,'Average Profit Margin'!W9,February!K8:K10) -> 275 | Z9: =SUMIF(March!B8:B71,'Average Profit Margin'!W9,March!K8:K10) -> 675 | AA9: =SUMIF(April!B8:B71,'Average Profit Margin'!W9,April!K8:K10) -> 1525 | AB9: =SUMIF(May!B8:B71,'Average Profit Margin'!W9,May!K8:K10) -> 1100 | AC9: =SUMIF(June!B8:B71,'Average Profit Margin'!W9,June!K8:K10) -> 1475 | AD9: =X9+Y9+Z9+AA9+AB9+AC9 -> 5575
A10: Chart Paper | B10: =SUMIF(January!B9:B72,'Average Profit Margin'!A10,January!I9:I11) -> 264 | C10: =SUMIF(February!B9:B72,'Average Profit Margin'!A10,February!I9:I11) -> 256 | D10: =SUMIF(March!B9:B72,'Average Profit Margin'!A10,March!I9:I11) -> 322 | E10: =SUMIF(April!B9:B72,'Average Profit Margin'!A10,April!I9:I11) -> 458 | F10: =SUMIF(May!B9:B72,'Average Profit Margin'!A10,May!I9:I11) -> 630 | G10: =SUMIF(June!B9:B72,'Average Profit Margin'!A10,June!I9:I11) -> 1006 | H10: =B10+C10+D10+E10+F10+G10 -> 2936 | M10: Chart Paper | N10: =SUMIF(January!B9:B72,'Average Profit Margin'!M10,January!J9:J11) -> 144 | O10: =SUMIF(February!B9:B72,'Average Profit Margin'!M10,February!J9:J11) -> 141 | P10: =SUMIF(March!B9:B72,'Average Profit Margin'!M10,March!J9:J11) -> 177 | Q10: =SUMIF(April!B9:B72,'Average Profit Margin'!M10,April!J9:J11) -> 253 | R10: =SUMIF(May!B9:B72,'Average Profit Margin'!M10,May!J9:J11) -> 340 | S10: =SUMIF(June!B9:B72,'Average Profit Margin'!M10,June!J9:J11) -> 551 | T10: =N10+O10+P10+Q10+R10+S10 -> 1606 | W10: Chart Paper | X10: =SUMIF(January!B9:B72,'Average Profit Margin'!W10,January!K9:K11) -> 120 | Y10: =SUMIF(February!B9:B72,'Average Profit Margin'!W10,February!K9:K11) -> 115 | Z10: =SUMIF(March!B9:B72,'Average Profit Margin'!W10,March!K9:K11) -> 145 | AA10: =SUMIF(April!B9:B72,'Average Profit Margin'!W10,April!K9:K11) -> 205 | AB10: =SUMIF(May!B9:B72,'Average Profit Margin'!W10,May!K9:K11) -> 290 | AC10: =SUMIF(June!B9:B72,'Average Profit Margin'!W10,June!K9:K11) -> 455 | AD10: =X10+Y10+Z10+AA10+AB10+AC10 -> 1330
A11: Adhesive | B11: =SUMIF(January!B10:B73,'Average Profit Margin'!A11,January!I10:I12) -> 3875 | C11: =SUMIF(February!B10:B73,'Average Profit Margin'!A11,February!I10:I12) -> 3110 | D11: =SUMIF(March!B10:B73,'Average Profit Margin'!A11,March!I10:I12) -> 3375 | E11: =SUMIF(April!B10:B73,'Average Profit Margin'!A11,April!I10:I12) -> 4515 | F11: =SUMIF(May!B10:B73,'Average Profit Margin'!A11,May!I10:I12) -> 4370 | G11: =SUMIF(June!B10:B73,'Average Profit Margin'!A11,June!I10:I12) -> 6130 | H11: =B11+C11+D11+E11+F11+G11 -> 25375 | M11: Adhesive | N11: =SUMIF(January!B10:B73,'Average Profit Margin'!M11,January!J10:J12) -> 2905 | O11: =SUMIF(February!B10:B73,'Average Profit Margin'!M11,February!J10:J12) -> 2335 | P11: =SUMIF(March!B10:B73,'Average Profit Margin'!M11,March!J10:J12) -> 2535 | Q11: =SUMIF(April!B10:B73,'Average Profit Margin'!M11,April!J10:J12) -> 3390 | R11: =SUMIF(May!B10:B73,'Average Profit Margin'!M11,May!J10:J12) -> 3285 | S11: =SUMIF(June!B10:B73,'Average Profit Margin'!M11,June!J10:J12) -> 4600 | T11: =N11+O11+P11+Q11+R11+S11 -> 19050 | W11: Adhesive | X11: =SUMIF(January!B10:B73,'Average Profit Margin'!W11,January!K10:K12) -> 970 | Y11: =SUMIF(February!B10:B73,'Average Profit Margin'!W11,February!K10:K12) -> 775 | Z11: =SUMIF(March!B10:B73,'Average Profit Margin'!W11,March!K10:K12) -> 840 | AA11: =SUMIF(April!B10:B73,'Average Profit Margin'!W11,April!K10:K12) -> 1125 | AB11: =SUMIF(May!B10:B73,'Average Profit Margin'!W11,May!K10:K12) -> 1085 | AC11: =SUMIF(June!B10:B73,'Average Profit Margin'!W11,June!K10:K12) -> 1530 | AD11: =X11+Y11+Z11+AA11+AB11+AC11 -> 6325
A12: Color Pencils | B12: =SUMIF(January!B11:B74,'Average Profit Margin'!A12,January!I11:I13) -> 7110 | C12: =SUMIF(February!B11:B74,'Average Profit Margin'!A12,February!I11:I13) -> 4405 | D12: =SUMIF(March!B11:B74,'Average Profit Margin'!A12,March!I11:I13) -> 8350 | E12: =SUMIF(April!B11:B74,'Average Profit Margin'!A12,April!I11:I13) -> 13220 | F12: =SUMIF(May!B11:B74,'Average Profit Margin'!A12,May!I11:I13) -> 11090 | G12: =SUMIF(June!B11:B74,'Average Profit Margin'!A12,June!I11:I13) -> 14430 | H12: =B12+C12+D12+E12+F12+G12 -> 58605 | M12: Color Pencils | N12: =SUMIF(January!B11:B74,'Average Profit Margin'!M12,January!J11:J13) -> 5530 | O12: =SUMIF(February!B11:B74,'Average Profit Margin'!M12,February!J11:J13) -> 3315 | P12: =SUMIF(March!B11:B74,'Average Profit Margin'!M12,March!J11:J13) -> 6515 | Q12: =SUMIF(April!B11:B74,'Average Profit Margin'!M12,April!J11:J13) -> 10315 | R12: =SUMIF(May!B11:B74,'Average Profit Margin'!M12,May!J11:J13) -> 8585 | S12: =SUMIF(June!B11:B74,'Average Profit Margin'!M12,June!J11:J13) -> 11110 | T12: =N12+O12+P12+Q12+R12+S12 -> 45370 | W12: Color Pencils | X12: =SUMIF(January!B11:B74,'Average Profit Margin'!W12,January!K11:K13) -> 1580 | Y12: =SUMIF(February!B11:B74,'Average Profit Margin'!W12,February!K11:K13) -> 1090 | Z12: =SUMIF(March!B11:B74,'Average Profit Margin'!W12,March!K11:K13) -> 1835 | AA12: =SUMIF(April!B11:B74,'Average Profit Margin'!W12,April!K11:K13) -> 2905 | AB12: =SUMIF(May!B11:B74,'Average Profit Margin'!W12,May!K11:K13) -> 2505 | AC12: =SUMIF(June!B11:B74,'Average Profit Margin'!W12,June!K11:K13) -> 3320 | AD12: =X12+Y12+Z12+AA12+AB12+AC12 -> 13235
A13: Project File | B13: =SUMIF(January!B12:B75,'Average Profit Margin'!A13,January!I12:I14) -> 760 | C13: =SUMIF(February!B12:B75,'Average Profit Margin'!A13,February!I12:I14) -> 560 | D13: =SUMIF(March!B12:B75,'Average Profit Margin'!A13,March!I12:I14) -> 640 | E13: =SUMIF(April!B12:B75,'Average Profit Margin'!A13,April!I12:I14) -> 1040 | F13: =SUMIF(May!B12:B75,'Average Profit Margin'!A13,May!I12:I14) -> 1470 | G13: =SUMIF(June!B12:B75,'Average Profit Margin'!A13,June!I12:I14) -> 1300 | H13: =B13+C13+D13+E13+F13+G13 -> 5770 | M13: Project File | N13: =SUMIF(January!B12:B75,'Average Profit Margin'!M13,January!J12:J14) -> 488 | O13: =SUMIF(February!B12:B75,'Average Profit Margin'!M13,February!J12:J14) -> 360 | P13: =SUMIF(March!B12:B75,'Average Profit Margin'!M13,March!J12:J14) -> 408 | Q13: =SUMIF(April!B12:B75,'Average Profit Margin'!M13,April!J12:J14) -> 664 | R13: =SUMIF(May!B12:B75,'Average Profit Margin'!M13,May!J12:J14) -> 948 | S13: =SUMIF(June!B12:B75,'Average Profit Margin'!M13,June!J12:J14) -> 836 | T13: =N13+O13+P13+Q13+R13+S13 -> 3704 | W13: Project File | X13: =SUMIF(January!B12:B75,'Average Profit Margin'!W13,January!K12:K14) -> 272 | Y13: =SUMIF(February!B12:B75,'Average Profit Margin'!W13,February!K12:K14) -> 200 | Z13: =SUMIF(March!B12:B75,'Average Profit Margin'!W13,March!K12:K14) -> 232 | AA13: =SUMIF(April!B12:B75,'Average Profit Margin'!W13,April!K12:K14) -> 376 | AB13: =SUMIF(May!B12:B75,'Average Profit Margin'!W13,May!K12:K14) -> 522 | AC13: =SUMIF(June!B12:B75,'Average Profit Margin'!W13,June!K12:K14) -> 464 | AD13: =X13+Y13+Z13+AA13+AB13+AC13 -> 2066
A14: Stapler | B14: =SUMIF(January!B13:B76,'Average Profit Margin'!A14,January!I13:I15) -> 1080 | C14: =SUMIF(February!B13:B76,'Average Profit Margin'!A14,February!I13:I15) -> 500 | D14: =SUMIF(March!B13:B76,'Average Profit Margin'!A14,March!I13:I15) -> 1000 | E14: =SUMIF(April!B13:B76,'Average Profit Margin'!A14,April!I13:I15) -> 1060 | F14: =SUMIF(May!B13:B76,'Average Profit Margin'!A14,May!I13:I15) -> 1200 | G14: =SUMIF(June!B13:B76,'Average Profit Margin'!A14,June!I13:I15) -> 2080 | H14: =B14+C14+D14+E14+F14+G14 -> 6920 | M14: Stapler | N14: =SUMIF(January!B13:B76,'Average Profit Margin'!M14,January!J13:J15) -> 594 | O14: =SUMIF(February!B13:B76,'Average Profit Margin'!M14,February!J13:J15) -> 229 | P14: =SUMIF(March!B13:B76,'Average Profit Margin'!M14,March!J13:J15) -> 539 | Q14: =SUMIF(April!B13:B76,'Average Profit Margin'!M14,April!J13:J15) -> 533 | R14: =SUMIF(May!B13:B76,'Average Profit Margin'!M14,May!J13:J15) -> 636 | S14: =SUMIF(June!B13:B76,'Average Profit Margin'!M14,June!J13:J15) -> 1133 | T14: =N14+O14+P14+Q14+R14+S14 -> 3664 | W14: Stapler | X14: =SUMIF(January!B13:B76,'Average Profit Margin'!W14,January!K13:K15) -> 486 | Y14: =SUMIF(February!B13:B76,'Average Profit Margin'!W14,February!K13:K15) -> 271 | Z14: =SUMIF(March!B13:B76,'Average Profit Margin'!W14,March!K13:K15) -> 461 | AA14: =SUMIF(April!B13:B76,'Average Profit Margin'!W14,April!K13:K15) -> 527 | AB14: =SUMIF(May!B13:B76,'Average Profit Margin'!W14,May!K13:K15) -> 564 | AC14: =SUMIF(June!B13:B76,'Average Profit Margin'!W14,June!K13:K15) -> 947 | AD14: =X14+Y14+Z14+AA14+AB14+AC14 -> 3256
A15: Drawing Book | B15: =SUMIF(January!B14:B77,'Average Profit Margin'!A15,January!I14:I16) -> 3420 | C15: =SUMIF(February!B14:B77,'Average Profit Margin'!A15,February!I14:I16) -> 1870 | D15: =SUMIF(March!B14:B77,'Average Profit Margin'!A15,March!I14:I16) -> 3645 | E15: =SUMIF(April!B14:B77,'Average Profit Margin'!A15,April!I14:I16) -> 6435 | F15: =SUMIF(May!B14:B77,'Average Profit Margin'!A15,May!I14:I16) -> 4780 | G15: =SUMIF(June!B14:B77,'Average Profit Margin'!A15,June!I14:I16) -> 7470 | H15: =B15+C15+D15+E15+F15+G15 -> 27620 | M15: Drawing Book | N15: =SUMIF(January!B14:B77,'Average Profit Margin'!M15,January!J14:J16) -> 2650 | O15: =SUMIF(February!B14:B77,'Average Profit Margin'!M15,February!J14:J16) -> 1455 | P15: =SUMIF(March!B14:B77,'Average Profit Margin'!M15,March!J14:J16) -> 2825 | Q15: =SUMIF(April!B14:B77,'Average Profit Margin'!M15,April!J14:J16) -> 5020 | R15: =SUMIF(May!B14:B77,'Average Profit Margin'!M15,May!J14:J16) -> 3720 | S15: =SUMIF(June!B14:B77,'Average Profit Margin'!M15,June!J14:J16) -> 5755 | T15: =N15+O15+P15+Q15+R15+S15 -> 21425 | W15: Drawing Book | X15: =SUMIF(January!B14:B77,'Average Profit Margin'!W15,January!K14:K16) -> 770 | Y15: =SUMIF(February!B14:B77,'Average Profit Margin'!W15,February!K14:K16) -> 415 | Z15: =SUMIF(March!B14:B77,'Average Profit Margin'!W15,March!K14:K16) -> 820 | AA15: =SUMIF(April!B14:B77,'Average Profit Margin'!W15,April!K14:K16) -> 1415 | AB15: =SUMIF(May!B14:B77,'Average Profit Margin'!W15,May!K14:K16) -> 1060 | AC15: =SUMIF(June!B14:B77,'Average Profit Margin'!W15,June!K14:K16) -> 1715 | AD15: =X15+Y15+Z15+AA15+AB15+AC15 -> 6195
... A20: A4 Sheets | B20: =SUMIF(January!B19:B82,'Average Profit Margin'!A20,January!I19:I21) -> 484 | C20: =SUMIF(February!B19:B82,'Average Profit Margin'!A20,February!I19:I21) -> 367 | D20: =SUMIF(March!B19:B82,'Average Profit Margin'!A20,March!I19:I21) -> 491 | E20: =SUMIF(April!B19:B82,'Average Profit Margin'!A20,April!I19:I21) -> 652 | F20: =SUMIF(May!B19:B82,'Average Profit Margin'!A20,May!I19:I21) -> 839 | G20: =SUMIF(June!B19:B82,'Average Profit Margin'!A20,June!I19:I21) -> 1164 | H20: =B20+C20+D20+E20+F20+G20 -> 3997 | M20: A4 Sheets | N20: =SUMIF(January!B19:B82,'Average Profit Margin'!M20,January!J19:J21) -> 242 | O20: =SUMIF(February!B19:B82,'Average Profit Margin'!M20,February!J19:J21) -> 184 | P20: =SUMIF(March!B19:B82,'Average Profit Margin'!M20,March!J19:J21) -> 251 | Q20: =SUMIF(April!B19:B82,'Average Profit Margin'!M20,April!J19:J21) -> 326 | R20: =SUMIF(May!B19:B82,'Average Profit Margin'!M20,May!J19:J21) -> 430 | S20: =SUMIF(June!B19:B82,'Average Profit Margin'!M20,June!J19:J21) -> 582 | T20: =N20+O20+P20+Q20+R20+S20 -> 2015 | W20: A4 Sheets | X20: =SUMIF(January!B19:B82,'Average Profit Margin'!W20,January!K19:K21) -> 242 | Y20: =SUMIF(February!B19:B82,'Average Profit Margin'!W20,February!K19:K21) -> 183 | Z20: =SUMIF(March!B19:B82,'Average Profit Margin'!W20,March!K19:K21) -> 240 | AA20: =SUMIF(April!B19:B82,'Average Profit Margin'!W20,April!K19:K21) -> 326 | AB20: =SUMIF(May!B19:B82,'Average Profit Margin'!W20,May!K19:K21) -> 409 | AC20: =SUMIF(June!B19:B82,'Average Profit Margin'!W20,June!K19:K21) -> 582 | AD20: =X20+Y20+Z20+AA20+AB20+AC20 -> 1982
A22: Average Profit Margin Table
A23: Product Type | B23: Total Revenue | C23: Total Cost | D23: Total Profit | E23: Average Profit | I23: Product Type | J23: Average Profit Margin (%)
A24: {=_xlfn.UNIQUE(January!B2:B65)} -> Spiral Notebook | B24: 76640 | C24: 63870 | D24: 12770 | E24: =D24/B24 -> 0.16662317 | I24: A4 Sheets | J24: 49.6
A25: Ruled Notebook | B25: 32690 | C25: 21750 | D25: 10940 | E25: =D25/B25 -> 0.33465892 | I25: Stapler | J25: 47.1
A26: Unruled Notebook | B26: 11200 | C26: 7090 | D26: 4110 | E26: =D26/B26 -> 0.36696429 | I26: Chart Paper | J26: 45.3
A27: Register | B27: 44026 | C27: 35890 | D27: 8136 | E27: =D27/B27 -> 0.18479989 | I27: Ruled Notebook | J27: 33.5
A28: Pencils | B28: 43680 | C28: 31545 | D28: 12135 | E28: =D28/B28 -> 0.27781593 | I28: Adhesive Tape | J28: 28.9
A29: Pens | B29: 105270 | C29: 81875 | D29: 23395 | E29: =D29/B29 -> 0.22223805 | I29: Color Pencils | J29: 22.6
A30: Geometry Box | B30: 33515 | C30: 27940 | D30: 5575 | E30: =D30/B30 -> 0.16634343 | I30: Water Colors and Oil Paints | J30: 22.6
A31: Chart Paper | B31: 2936 | C31: 1606 | D31: 1330 | E31: =D31/B31 -> 0.45299728 | I31: Pens | J31: 22.2
A32: Adhesive | B32: 25375 | C32: 19050 | D32: 6325 | E32: =D32/B32 -> 0.24926108 | I32: Spiral Notebook | J32: 16.7
A33: Color Pencils | B33: 58605 | C33: 45370 | D33: 13235 | E33: =D33/B33 -> 0.22583397 | I33: Geometry Box | J33: 16.6
A34: Project File | B34: 5770 | C34: 3704 | D34: 2066 | E34: =D34/B34 -> 0.35805893
A35: Stapler | B35: 6920 | C35: 3664 | D35: 3256 | E35: =D35/B35 -> 0.47052023
A36: Drawing Book | B36: 27620 | C36: 21425 | D36: 6195 | E36: =D36/B36 -> 0.22429399
A37: Adhesive Tape | B37: 31175 | C37: 22165 | D37: 9010 | E37: =D37/B37 -> 0.28901363
A38: Markers | B38: 7845 | C38: 4380 | D38: 3465 | E38: =D38/B38 -> 0.4416826
A39: Water Colors and Oil paints | B39: 63675 | C39: 49265 | D39: 14410 | E39: =D39/B39 -> 0.22630546
A40: Notebook Cover | B40: 9280 | C40: 5773 | D40: 3507 | E40: =D40/B40 -> 0.37790948
A41: A4 Sheets | B41: 3997 | C41: 2015 | D41: 1982 | E41: =D41/B41 -> 0.4958719

Sheet Inventory Sales
A1: Month Name | B1: Units Sold
A2: Jan | B2: 998
A3: Feb | B3: 708
A4: Mar | B4: 972
A5: Apr | B5: 1651
A6: May | B6: 1298
A7: Jun | B7: 2201

Sheet Stock out
O1: Product Type | P1: Stock-to-Sales Ratio
O2: A4 Sheets | P2: 2.62
O3: Adhesive | P3: 2.28
O4: Adhesive Tape | P4: 3.41
O5: Chart Paper | P5: 2.24
O6: Color Pencils | P6: 1.92
O7: Drawing Book | P7: 4.39
O8: Geometry Box | P8: 2.88
O9: Markers | P9: 2.85
O10: Notebook Cover | P10: 3.99
O11: Pencils | P11: 1.76
O12: Pens | P12: 1.78
O13: Project File | P13: 1.77
... O19: Water Colors and Oil Paints | P19: 4.23

Sheet ABC analysis
A1: Product Type | B1: Total Revenue | C1: Cumulative Percentage | D1: Cumulative Revenue
A2: Pens | B2: 105270 | C2: 0.1784 | D2: 105270
A3: Spiral Notebook | B3: 76640 | C3: 0.3082 | D3: 181910
A4: Water Colors and Oil paints | B4: 63675 | C4: 0.4161 | D4: 245585
A5: Color Pencils | B5: 58605 | C5: 0.5154 | D5: 304190
A6: Register | B6: 44026 | C6: 0.59 | D6: 348216
A7: Pencils | B7: 43680 | C7: 0.664 | D7: 391896
A8: Geometry Box | B8: 33515 | C8: 0.7208 | D8: 425411
A9: Ruled Notebook | B9: 32690 | C9: 0.7762 | D9: 458101
A10: Adhesive Tape | B10: 31175 | C10: 0.829 | D10: 489276
A11: Drawing Book | B11: 27620 | C11: 0.8758 | D11: 516896
A12: Adhesive | B12: 25375 | C12: 0.9188 | D12: 542271
A13: Unruled Notebook | B13: 11200 | C13: 0.9377 | D13: 553471
... A19: Chart Paper | B19: 2936 | C19: 1 | D19: 590219
A36: Category Name | B36: Jan | C36: Feb | D36: March | E36: April | F36: May | G36: June | H36: Total Revenue | I36: Cummulative Revenue | J36: Cummulative Percentage
A37: Pens | H37: 105270
A38: Spiral Notebook | B38: 7360 | C38: 4730 | D38: 8785 | E38: 19925 | F38: 11015 | G38: 24825 | H38: =SUM(B38+C38+D38+E38+F38+G38) -> 76640
A39: Color Pencils | B39: 7110 | C39: 4405 | D39: 8350 | E39: 13220 | F39: 11090 | G39: 14430 | H39: =SUM(B39+C39+D39+E39+F39+G39) -> 58605
A40: Pencils | B40: 7120 | C40: 5100 | D40: 6140 | E40: 9060 | F40: 5940 | G40: 10320 | H40: =SUM(B40+C40+D40+E40+F40+G40) -> 43680
A41: Ruled Notebooks | B41: 3035 | C41: 2250 | D41: 3520 | E41: 6905 | F41: 4480 | G41: 10500 | H41: =SUM(B41+C41+D41+E41+F41+G41) -> 30690
A42: Adhesive | B42: 3875 | C42: 3110 | D42: 3375 | E42: 4515 | F42: 4370 | G42: 6130 | H42: =SUM(B42+C42+D42+E42+F42+G42) -> 25375
A43: Markers | B43: 1115 | C43: 800 | D43: 985 | E43: 1670 | F43: 1350 | G43: 1925 | H43: =SUM(B43+C43+D43+E43+F43+G43) -> 7845
G44: Total | H44: =SUM(H37+H38+H39+H43+H42+H41+H40) -> 348105

Sheet Highest selling
A1: Product Name | B1: Units Sold
A2: Cello Finegrip (10 pens) | B2: 217
A3: Nataraj 621 Writing Pencils | B3: 208
A4: Apsara Matt Magic 2.0 | B4: 195
A5: Classmate Pulse Spiral Notebook | B5: 191
A6: Pentonic 0.7mm Pens | B6: 186
A7: Camlin White Board Marker | B7: 178
A8: Dom's Extra Dark Pencils | B8: 170
A9: Navneet Long Book 76 Pages | B9: 165
A10: Classmate Soft Cover Notebook | B10: 160
A11: Camlin Geometry Box | B11: 155

Sheet Turnover Ratio
A1: Inventory Turnover Ratio by Category
A2: Product Type | B2: January | C2: February | D2: March | E2: April | F2: May | G2: June
A3: A4 Sheets | B3: 0.45 | C3: 0.28 | D3: 0.33 | E3: 0.41 | F3: 0.53 | G3: 0.77
A4: Adhesive | B4: 0.47 | C4: 0.38 | D4: 0.45 | E4: 0.57 | F4: 0.46 | G4: 0.58
A5: Adhhesive Tape | B5: 0.41 | C5: 0.25 | D5: 0.27 | E5: 0.41 | F5: 0.37 | G5: 0.5
A6: Chart Paper | B6: 0.4 | C6: 0.32 | D6: 0.38 | E6: 0.49 | F6: 0.68 | G6: 1.14
A7: Color Pencils | B7: 0.54 | C7: 0.42 | D7: 0.66 | E7: 0.92 | F7: 0.61 | G7: 0.67
A8: Pens | B8: 0.62 | C8: 0.58 | D8: 0.71 | E8: 0.85 | F8: 0.79 | G8: 0.92
A9: Water Colors/Oil Paints | B9: 0.38 | C9: 0.29 | D9: 0.41 | E9: 0.52 | F9: 0.55 | G9: 0.69

Sheet Units sold vs Selling price
A2: Product Type | B2: Selling Price | C2: Units Sold
A3: A4 Sheets | B3: 5 | C3: 155
A4: A4 Sheets | B4: 15 | C4: 130
A5: Adhesive | B5: 25 | C5: 131
A6: Adhesive | B6: 40 | C6: 139
A7: Pens | B7: 50 | C7: 744
A8: Pens | B8: 100 | C8: 1313
A9: Spiral Notebook | B9: 120 | C9: 191
A10: Spiral Notebook | B10: 185 | C10: 152
A11: Geometry Box | B11: 155 | C11: 53
A12: Geometry Box | B12: 200 | C12: 54
A13: Geometry Box | B13: 250 | C13: 58

Sheet Profit Contribution
A2: Prodiuct Type | B2: Total Profit
A3: Pens | B3: 23395
A4: Water Colors and Oil Paints | B4: 14410
A5: Color Pencils | B5: 13235
A6: Spiral Notebook | B6: 12770
A7: Pencils | B7: 12135
A8: Ruled Notebook | B8: 10940
A9: Other | B9: 54957
A25: Category | B25: Total Profit (₹)
A26: Writing Instruments | B26: 35530
A27: Art Supplies | B27: 33840
A28: Notebooks | B28: 27820
A29: Adhesives | B29: 15335
A30: Office Supplies | B30: 13458
A31: Geometry | B31: 5575
A32: Notebook Cover | B32: 3507
A33: Markers | B33: 3465
A34: Art Paper | B34: 3312
A37: Category | B37: Profit
A38: Writing Instruments | B38: 35530
A39: Art Supplies | B39: 33840
A40: Notebooks | B40: 27820
A41: Adhesives | B41: 15335
A42: Others | B42: =SUM(B30,B31,B32,B33,B34) -> 29317

Sheet Seasonal Demands
A1: Seasonal Demand by Product Categories
A2: Product Type | B2: January | C2: February | D2: March | E2: April | F2: May | G2: June
A3: A4 Sheets | B3: 54 | C3: 41 | D3: 55 | E3: 72 | F3: 93 | G3: 129
A4: Adhesive | B4: 80 | C4: 61 | D4: 66 | E4: 93 | F4: 87 | G4: 122
A5: Adhesive Tape | B5: 34 | C5: 27 | D5: 33 | E5: 55 | F5: 57 | G5: 86
A6: Chart Paper | B6: 24 | C6: 23 | D6: 29 | E6: 41 | F6: 58 | G6: 91
A7: Color Pencils | B7: 50 | C7: 35 | D7: 58 | E7: 89 | F7: 82 | G7: 102
A8: Drawing Book | B8: 38 | C8: 31 | D8: 45 | E8: 67 | F8: 73 | G8: 112
A9: Geometry Box | B9: 16 | C9: 8 | D9: 16 | E9: 32 | F9: 32 | G9: 38
A10: Markers | B10: 31 | C10: 25 | D10: 38 | E10: 56 | F10: 55 | G10: 91
A11: Notebook Cover | B11: 27 | C11: 21 | D11: 28 | E11: 44 | F11: 48 | G11: 78
A12: Pencils | B12: 121 | C12: 92 | D12: 115 | E12: 153 | F12: 115 | G12: 174
A13: Pens | B13: 215 | C13: 168 | D13: 168 | E13: 250 | F13: 208 | G13: 304
A14: Project File | B14: 28 | C14: 22 | D14: 26 | E14: 42 | F14: 48 | G14: 66
... A19: Water Colors and Oil paints | B19: 52 | C19: 27 | D19: 52 | E19: 90 | F19: 68 | G19: 132
A23: Product Type | B23: January | C23: February | D23: March | E23: April | F23: May | G23: June
A24: A4 Sheets | B24: 54 | C24: 41 | D24: 55 | E24: 72 | F24: 93 | G24: 129
A25: Adhesive | B25: 80 | C25: 61 | D25: 66 | E25: 93 | F25: 87 | G25: 122
A27: Ruled Notebook | B27: 63 | C27: 47 | D27: 78 | E27: 189 | F27: 97 | G27: 231
A28: Spiral Notebook | B28: 48 | C28: 31 | D28: 58 | E28: 131 | F28: 72 | G28: 163
A29: Pencils | B29: 121 | C29: 92 | D29: 115 | E29: 153 | F29: 115 | G29: 174
A30: Pens | B30: 215 | C30: 168 | D30: 168 | E30: 250 | F30: 208 | G30: 304
